<?xml version="1.0" encoding="utf-8"?>
<SoundBanksInfo Platform="Windows" BasePlatform="Windows" SchemaVersion="12" SoundbankVersion="135">
	<RootPaths>
		<ProjectRoot>Z:\DeadByDaylight_Unreal\DeadByDaylight\Content_Raw\Audio\Wwise_2019_2_5_Hubble\</ProjectRoot>
		<SourceFilesRoot>Z:\DeadByDaylight_Unreal\DeadByDaylight\Content_Raw\Audio\Wwise_2019_2_5_Hubble\.cache\Windows\</SourceFilesRoot>
		<SoundBanksRoot>Z:\DeadByDaylight_Hubble_UGS\UnrealEngine\DeadByDaylight\Content\WwiseAudio\Windows\</SoundBanksRoot>
		<ExternalSourcesInputFile></ExternalSourcesInputFile>
		<ExternalSourcesOutputRoot>Z:\DeadByDaylight_Unreal\DeadByDaylight\Content_Raw\Audio\Wwise_2019_2_5_Hubble\GeneratedSoundBanks\Windows</ExternalSourcesOutputRoot>
	</RootPaths>
	<SoundBanks>
		<SoundBank Id="1457560507" GUID="{712E0B1B-B724-4F74-9A1B-3F108434E43F}" Language="SFX">
			<ObjectPath>\SoundBanks\CHARACTER\KILLER\KLR_20</ObjectPath>
			<ShortName>KLR_20</ShortName>
			<Path>KLR_20.bnk</Path>
			<IncludedEvents>
				<Event Id="598896019" Name="AudioEvent_K00_WPN_Attack_Stop" ObjectPath="\Events\IMPACT\IMPACT\AudioEvent_K00_WPN_Attack_Stop" GUID="{AAA7D380-188D-49BE-B7FD-54FD00E3A014}" MaxAttenuation="0.000000" DurationType="OneShot" DurationMin="0.000000" DurationMax="0.000000"/>
				<Event Id="2755638078" Name="AudioEvent_K20_WPN_COMMON_Sword_Down_left" ObjectPath="\Events\CHARACTER\KILLER\KLR_20_Wales\K20_WEAPON\AudioEvent_K20_WPN_COMMON_Sword_Down_left" GUID="{B8883BCF-FA4E-4A1F-BC31-9A6F148D64D3}" MaxAttenuation="1900.000000" DurationType="OneShot" DurationMin="0.786667" DurationMax="1.093375">
					<IncludedMemoryFiles>
						<File Id="140164873" Language="SFX">
							<ShortName>Weapons\K20_Wales_Sword\sfx_wpm_k20_wales_attack_C_Impact_01.wav</ShortName>
							<Path>SFX\Weapons\K20_Wales_Sword\sfx_wpm_k20_wales_attack_C_Impact_01_7FA8D501.wem</Path>
						</File>
						<File Id="594368897" Language="SFX">
							<ShortName>Weapons\K20_Wales_Sword\sfx_wpm_k20_wales_attack_C_Impact_03.wav</ShortName>
							<Path>SFX\Weapons\K20_Wales_Sword\sfx_wpm_k20_wales_attack_C_Impact_03_7FA8D501.wem</Path>
						</File>
						<File Id="654486328" Language="SFX">
							<ShortName>Weapons\K20_Wales_Sword\sfx_wpm_k20_wales_attack_C_Impact_02.wav</ShortName>
							<Path>SFX\Weapons\K20_Wales_Sword\sfx_wpm_k20_wales_attack_C_Impact_02_7FA8D501.wem</Path>
						</File>
					</IncludedMemoryFiles>
					<ActionPostEvent>
						<ActionPostEventEntry Id="598896019" Name="AudioEvent_K00_WPN_Attack_Stop" ObjectPath="\Events\IMPACT\IMPACT\AudioEvent_K00_WPN_Attack_Stop" GUID="{AAA7D380-188D-49BE-B7FD-54FD00E3A014}"/>
					</ActionPostEvent>
					<AuxBusSends>
						<AuxBus Id="286574509" Name="MENU_KLR_00_COMMON" ObjectPath="\Master-Mixer Hierarchy\Default Work Unit\Master Audio Bus\SFX\MENU\MENU_OBJECT\MENU_KILLER\MENU_KLR_00_COMMON" GUID="{E64B324D-8F4B-4D04-AAC1-282FD4D9B765}"/>
					</AuxBusSends>
				</Event>
				<Event Id="3591377373" Name="AudioEvent_K20_WPN_COMMON_Sword_Down_Right" ObjectPath="\Events\CHARACTER\KILLER\KLR_20_Wales\K20_WEAPON\AudioEvent_K20_WPN_COMMON_Sword_Down_Right" GUID="{14FD8B25-FF1E-40D2-9060-26F949C2CA71}" MaxAttenuation="1900.000000" DurationType="OneShot" DurationMin="0.786667" DurationMax="1.093375">
					<IncludedMemoryFiles>
						<File Id="140164873" Language="SFX">
							<ShortName>Weapons\K20_Wales_Sword\sfx_wpm_k20_wales_attack_C_Impact_01.wav</ShortName>
							<Path>SFX\Weapons\K20_Wales_Sword\sfx_wpm_k20_wales_attack_C_Impact_01_7FA8D501.wem</Path>
						</File>
						<File Id="594368897" Language="SFX">
							<ShortName>Weapons\K20_Wales_Sword\sfx_wpm_k20_wales_attack_C_Impact_03.wav</ShortName>
							<Path>SFX\Weapons\K20_Wales_Sword\sfx_wpm_k20_wales_attack_C_Impact_03_7FA8D501.wem</Path>
						</File>
						<File Id="654486328" Language="SFX">
							<ShortName>Weapons\K20_Wales_Sword\sfx_wpm_k20_wales_attack_C_Impact_02.wav</ShortName>
							<Path>SFX\Weapons\K20_Wales_Sword\sfx_wpm_k20_wales_attack_C_Impact_02_7FA8D501.wem</Path>
						</File>
					</IncludedMemoryFiles>
					<ActionPostEvent>
						<ActionPostEventEntry Id="598896019" Name="AudioEvent_K00_WPN_Attack_Stop" ObjectPath="\Events\IMPACT\IMPACT\AudioEvent_K00_WPN_Attack_Stop" GUID="{AAA7D380-188D-49BE-B7FD-54FD00E3A014}"/>
					</ActionPostEvent>
					<AuxBusSends>
						<AuxBus Id="286574509" Name="MENU_KLR_00_COMMON" ObjectPath="\Master-Mixer Hierarchy\Default Work Unit\Master Audio Bus\SFX\MENU\MENU_OBJECT\MENU_KILLER\MENU_KLR_00_COMMON" GUID="{E64B324D-8F4B-4D04-AAC1-282FD4D9B765}"/>
					</AuxBusSends>
				</Event>
				<Event Id="1234801033" Name="AudioEvent_K20_WPN_COMMON_Sword_Scrap" ObjectPath="\Events\CHARACTER\KILLER\KLR_20_Wales\K20_WEAPON\AudioEvent_K20_WPN_COMMON_Sword_Scrap" GUID="{7ACCC8B6-AA0C-407C-B15E-92997E0BAE36}" MaxAttenuation="1900.000000" DurationType="OneShot" DurationMin="1.000000" DurationMax="1.022917">
					<IncludedMemoryFiles>
						<File Id="18212406" Language="SFX">
							<ShortName>Weapons\K20_Wales_Sword\sfx_wpn_k20_friction_common_dirt_06.wav</ShortName>
							<Path>SFX\Weapons\K20_Wales_Sword\sfx_wpn_k20_friction_common_dirt_06_7FA8D501.wem</Path>
						</File>
						<File Id="38867555" Language="SFX">
							<ShortName>Weapons\K20_Wales_Sword\sfx_wpn_k20_friction_common_wood_02.wav</ShortName>
							<Path>SFX\Weapons\K20_Wales_Sword\sfx_wpn_k20_friction_common_wood_02_7FA8D501.wem</Path>
						</File>
						<File Id="48947754" Language="SFX">
							<ShortName>Weapons\K20_Wales_Sword\sfx_wpn_k20_friction_common_wood_07.wav</ShortName>
							<Path>SFX\Weapons\K20_Wales_Sword\sfx_wpn_k20_friction_common_wood_07_7FA8D501.wem</Path>
						</File>
						<File Id="130580187" Language="SFX">
							<ShortName>Weapons\K20_Wales_Sword\sfx_wpn_k20_friction_common_rock_01.wav</ShortName>
							<Path>SFX\Weapons\K20_Wales_Sword\sfx_wpn_k20_friction_common_rock_01_7FA8D501.wem</Path>
						</File>
						<File Id="139472822" Language="SFX">
							<ShortName>Weapons\K20_Wales_Sword\sfx_wpn_k20_friction_common_wood_05.wav</ShortName>
							<Path>SFX\Weapons\K20_Wales_Sword\sfx_wpn_k20_friction_common_wood_05_7FA8D501.wem</Path>
						</File>
						<File Id="165935524" Language="SFX">
							<ShortName>Weapons\K20_Wales_Sword\sfx_wpn_k20_friction_common_gravel_09.wav</ShortName>
							<Path>SFX\Weapons\K20_Wales_Sword\sfx_wpn_k20_friction_common_gravel_09_7FA8D501.wem</Path>
						</File>
						<File Id="176270510" Language="SFX">
							<ShortName>Weapons\K20_Wales_Sword\sfx_wpn_k20_friction_common_wood_09.wav</ShortName>
							<Path>SFX\Weapons\K20_Wales_Sword\sfx_wpn_k20_friction_common_wood_09_7FA8D501.wem</Path>
						</File>
						<File Id="179057823" Language="SFX">
							<ShortName>Weapons\K20_Wales_Sword\sfx_wpn_k20_friction_common_dirt_02.wav</ShortName>
							<Path>SFX\Weapons\K20_Wales_Sword\sfx_wpn_k20_friction_common_dirt_02_7FA8D501.wem</Path>
						</File>
						<File Id="249632149" Language="SFX">
							<ShortName>Weapons\K20_Wales_Sword\sfx_wpn_k20_friction_common_gravel_03.wav</ShortName>
							<Path>SFX\Weapons\K20_Wales_Sword\sfx_wpn_k20_friction_common_gravel_03_7FA8D501.wem</Path>
						</File>
						<File Id="279057875" Language="SFX">
							<ShortName>Weapons\K20_Wales_Sword\sfx_wpn_k20_friction_common_hard_07.wav</ShortName>
							<Path>SFX\Weapons\K20_Wales_Sword\sfx_wpn_k20_friction_common_hard_07_7FA8D501.wem</Path>
						</File>
						<File Id="294609085" Language="SFX">
							<ShortName>Weapons\K20_Wales_Sword\sfx_wpn_k20_friction_common_dirt_03.wav</ShortName>
							<Path>SFX\Weapons\K20_Wales_Sword\sfx_wpn_k20_friction_common_dirt_03_7FA8D501.wem</Path>
						</File>
						<File Id="329931730" Language="SFX">
							<ShortName>Weapons\K20_Wales_Sword\sfx_wpn_k20_friction_common_wood_08.wav</ShortName>
							<Path>SFX\Weapons\K20_Wales_Sword\sfx_wpn_k20_friction_common_wood_08_7FA8D501.wem</Path>
						</File>
						<File Id="411820885" Language="SFX">
							<ShortName>Weapons\K20_Wales_Sword\sfx_wpn_k20_friction_common_gravel_08.wav</ShortName>
							<Path>SFX\Weapons\K20_Wales_Sword\sfx_wpn_k20_friction_common_gravel_08_7FA8D501.wem</Path>
						</File>
						<File Id="417514232" Language="SFX">
							<ShortName>Weapons\K20_Wales_Sword\sfx_wpn_k20_friction_common_wood_01.wav</ShortName>
							<Path>SFX\Weapons\K20_Wales_Sword\sfx_wpn_k20_friction_common_wood_01_7FA8D501.wem</Path>
						</File>
						<File Id="429593179" Language="SFX">
							<ShortName>Weapons\K20_Wales_Sword\sfx_wpn_k20_friction_common_hard_03.wav</ShortName>
							<Path>SFX\Weapons\K20_Wales_Sword\sfx_wpn_k20_friction_common_hard_03_7FA8D501.wem</Path>
						</File>
						<File Id="448240839" Language="SFX">
							<ShortName>Weapons\K20_Wales_Sword\sfx_wpn_k20_friction_common_rock_03.wav</ShortName>
							<Path>SFX\Weapons\K20_Wales_Sword\sfx_wpn_k20_friction_common_rock_03_7FA8D501.wem</Path>
						</File>
						<File Id="460662443" Language="SFX">
							<ShortName>Weapons\K20_Wales_Sword\sfx_wpn_k20_friction_common_hard_09.wav</ShortName>
							<Path>SFX\Weapons\K20_Wales_Sword\sfx_wpn_k20_friction_common_hard_09_7FA8D501.wem</Path>
						</File>
						<File Id="462368658" Language="SFX">
							<ShortName>Weapons\K20_Wales_Sword\sfx_wpn_k20_friction_common_wood_04.wav</ShortName>
							<Path>SFX\Weapons\K20_Wales_Sword\sfx_wpn_k20_friction_common_wood_04_7FA8D501.wem</Path>
						</File>
						<File Id="512376643" Language="SFX">
							<ShortName>Weapons\K20_Wales_Sword\sfx_wpn_k20_friction_common_hard_05.wav</ShortName>
							<Path>SFX\Weapons\K20_Wales_Sword\sfx_wpn_k20_friction_common_hard_05_7FA8D501.wem</Path>
						</File>
						<File Id="547875919" Language="SFX">
							<ShortName>Weapons\K20_Wales_Sword\sfx_wpn_k20_friction_common_gravel_06.wav</ShortName>
							<Path>SFX\Weapons\K20_Wales_Sword\sfx_wpn_k20_friction_common_gravel_06_7FA8D501.wem</Path>
						</File>
						<File Id="561797458" Language="SFX">
							<ShortName>Weapons\K20_Wales_Sword\sfx_wpn_k20_friction_common_gravel_05.wav</ShortName>
							<Path>SFX\Weapons\K20_Wales_Sword\sfx_wpn_k20_friction_common_gravel_05_7FA8D501.wem</Path>
						</File>
						<File Id="597413932" Language="SFX">
							<ShortName>Weapons\K20_Wales_Sword\sfx_wpn_k20_friction_common_gravel_01.wav</ShortName>
							<Path>SFX\Weapons\K20_Wales_Sword\sfx_wpn_k20_friction_common_gravel_01_7FA8D501.wem</Path>
						</File>
						<File Id="742124219" Language="SFX">
							<ShortName>Weapons\K20_Wales_Sword\sfx_wpn_k20_friction_common_rock_04.wav</ShortName>
							<Path>SFX\Weapons\K20_Wales_Sword\sfx_wpn_k20_friction_common_rock_04_7FA8D501.wem</Path>
						</File>
						<File Id="788336267" Language="SFX">
							<ShortName>Weapons\K20_Wales_Sword\sfx_wpn_k20_friction_common_gravel_04.wav</ShortName>
							<Path>SFX\Weapons\K20_Wales_Sword\sfx_wpn_k20_friction_common_gravel_04_7FA8D501.wem</Path>
						</File>
						<File Id="803933617" Language="SFX">
							<ShortName>Weapons\K20_Wales_Sword\sfx_wpn_k20_friction_common_gravel_07.wav</ShortName>
							<Path>SFX\Weapons\K20_Wales_Sword\sfx_wpn_k20_friction_common_gravel_07_7FA8D501.wem</Path>
						</File>
						<File Id="825151950" Language="SFX">
							<ShortName>Weapons\K20_Wales_Sword\sfx_wpn_k20_friction_common_rock_02.wav</ShortName>
							<Path>SFX\Weapons\K20_Wales_Sword\sfx_wpn_k20_friction_common_rock_02_7FA8D501.wem</Path>
						</File>
						<File Id="833842946" Language="SFX">
							<ShortName>Weapons\K20_Wales_Sword\sfx_wpn_k20_friction_common_hard_10.wav</ShortName>
							<Path>SFX\Weapons\K20_Wales_Sword\sfx_wpn_k20_friction_common_hard_10_7FA8D501.wem</Path>
						</File>
						<File Id="847457520" Language="SFX">
							<ShortName>Weapons\K20_Wales_Sword\sfx_wpn_k20_friction_common_dirt_08.wav</ShortName>
							<Path>SFX\Weapons\K20_Wales_Sword\sfx_wpn_k20_friction_common_dirt_08_7FA8D501.wem</Path>
						</File>
						<File Id="849730144" Language="SFX">
							<ShortName>Weapons\K20_Wales_Sword\sfx_wpn_k20_friction_common_dirt_04.wav</ShortName>
							<Path>SFX\Weapons\K20_Wales_Sword\sfx_wpn_k20_friction_common_dirt_04_7FA8D501.wem</Path>
						</File>
						<File Id="871223500" Language="SFX">
							<ShortName>Weapons\K20_Wales_Sword\sfx_wpn_k20_friction_common_rock_05.wav</ShortName>
							<Path>SFX\Weapons\K20_Wales_Sword\sfx_wpn_k20_friction_common_rock_05_7FA8D501.wem</Path>
						</File>
						<File Id="899306645" Language="SFX">
							<ShortName>Weapons\K20_Wales_Sword\sfx_wpn_k20_friction_common_rock_07.wav</ShortName>
							<Path>SFX\Weapons\K20_Wales_Sword\sfx_wpn_k20_friction_common_rock_07_7FA8D501.wem</Path>
						</File>
						<File Id="904932362" Language="SFX">
							<ShortName>Weapons\K20_Wales_Sword\sfx_wpn_k20_friction_common_hard_08.wav</ShortName>
							<Path>SFX\Weapons\K20_Wales_Sword\sfx_wpn_k20_friction_common_hard_08_7FA8D501.wem</Path>
						</File>
						<File Id="969704456" Language="SFX">
							<ShortName>Weapons\K20_Wales_Sword\sfx_wpn_k20_friction_common_rock_06.wav</ShortName>
							<Path>SFX\Weapons\K20_Wales_Sword\sfx_wpn_k20_friction_common_rock_06_7FA8D501.wem</Path>
						</File>
						<File Id="984255218" Language="SFX">
							<ShortName>Weapons\K20_Wales_Sword\sfx_wpn_k20_friction_common_dirt_01.wav</ShortName>
							<Path>SFX\Weapons\K20_Wales_Sword\sfx_wpn_k20_friction_common_dirt_01_7FA8D501.wem</Path>
						</File>
						<File Id="1003119099" Language="SFX">
							<ShortName>Weapons\K20_Wales_Sword\sfx_wpn_k20_friction_common_dirt_07.wav</ShortName>
							<Path>SFX\Weapons\K20_Wales_Sword\sfx_wpn_k20_friction_common_dirt_07_7FA8D501.wem</Path>
						</File>
						<File Id="1016627027" Language="SFX">
							<ShortName>Weapons\K20_Wales_Sword\sfx_wpn_k20_friction_common_wood_06.wav</ShortName>
							<Path>SFX\Weapons\K20_Wales_Sword\sfx_wpn_k20_friction_common_wood_06_7FA8D501.wem</Path>
						</File>
						<File Id="1022069541" Language="SFX">
							<ShortName>Weapons\K20_Wales_Sword\sfx_wpn_k20_friction_common_wood_03.wav</ShortName>
							<Path>SFX\Weapons\K20_Wales_Sword\sfx_wpn_k20_friction_common_wood_03_7FA8D501.wem</Path>
						</File>
						<File Id="1063521285" Language="SFX">
							<ShortName>Weapons\K20_Wales_Sword\sfx_wpn_k20_friction_common_dirt_05.wav</ShortName>
							<Path>SFX\Weapons\K20_Wales_Sword\sfx_wpn_k20_friction_common_dirt_05_7FA8D501.wem</Path>
						</File>
						<File Id="1069686508" Language="SFX">
							<ShortName>Weapons\K20_Wales_Sword\sfx_wpn_k20_friction_common_gravel_02.wav</ShortName>
							<Path>SFX\Weapons\K20_Wales_Sword\sfx_wpn_k20_friction_common_gravel_02_7FA8D501.wem</Path>
						</File>
					</IncludedMemoryFiles>
					<DefaultSwitchValue>{A970F4EA-165B-4AC1-A78C-73F51FC9EA9D}</DefaultSwitchValue>
					<SwitchContainers>
						<SwitchContainer SwitchValue="{2792490C-9C7E-402A-B630-E1AEE10B67B0}">
							<Media>
								<File Id="512376643"/>
								<File Id="904932362"/>
								<File Id="460662443"/>
								<File Id="279057875"/>
								<File Id="833842946"/>
								<File Id="429593179"/>
							</Media>
						</SwitchContainer>
						<SwitchContainer SwitchValue="{1974DF19-3EAC-4718-94A9-7C7895513BA6}">
							<Media>
								<File Id="984255218"/>
								<File Id="179057823"/>
								<File Id="294609085"/>
								<File Id="847457520"/>
								<File Id="849730144"/>
								<File Id="1063521285"/>
								<File Id="1003119099"/>
								<File Id="18212406"/>
							</Media>
						</SwitchContainer>
						<SwitchContainer SwitchValue="{7CFDEF5B-7E20-4AA0-95F3-2DEDB396AF1F}">
							<Media>
								<File Id="130580187"/>
								<File Id="742124219"/>
								<File Id="899306645"/>
								<File Id="825151950"/>
								<File Id="448240839"/>
								<File Id="871223500"/>
								<File Id="969704456"/>
							</Media>
						</SwitchContainer>
						<SwitchContainer SwitchValue="{38536567-1A12-4FD1-8DCF-06603790A598}">
							<Media>
								<File Id="561797458"/>
								<File Id="597413932"/>
								<File Id="165935524"/>
								<File Id="249632149"/>
								<File Id="788336267"/>
								<File Id="411820885"/>
								<File Id="803933617"/>
								<File Id="1069686508"/>
								<File Id="547875919"/>
							</Media>
						</SwitchContainer>
						<SwitchContainer SwitchValue="{C1C58031-724C-47CC-9412-B4B8142690DD}">
							<Media>
								<File Id="417514232"/>
								<File Id="329931730"/>
								<File Id="462368658"/>
								<File Id="48947754"/>
								<File Id="1016627027"/>
								<File Id="38867555"/>
								<File Id="139472822"/>
								<File Id="1022069541"/>
								<File Id="176270510"/>
							</Media>
						</SwitchContainer>
					</SwitchContainers>
					<AuxBusSends>
						<AuxBus Id="286574509" Name="MENU_KLR_00_COMMON" ObjectPath="\Master-Mixer Hierarchy\Default Work Unit\Master Audio Bus\SFX\MENU\MENU_OBJECT\MENU_KILLER\MENU_KLR_00_COMMON" GUID="{E64B324D-8F4B-4D04-AAC1-282FD4D9B765}"/>
					</AuxBusSends>
				</Event>
				<Event Id="968769375" Name="AudioEvent_K20_WPN_COMMON_Sword_Trail_Start" ObjectPath="\Events\CHARACTER\KILLER\KLR_20_Wales\K20_WEAPON\AudioEvent_K20_WPN_COMMON_Sword_Trail_Start" GUID="{7B617FF5-4469-4899-9904-9E4E00536F4C}" MaxAttenuation="1900.000000" DurationType="OneShot" DurationMin="1.071561" DurationMax="1.281588">
					<IncludedMemoryFiles>
						<File Id="48171656" Language="SFX">
							<ShortName>Weapons\K20_Wales_Sword\sfx_wpn_k20_trail_start_a_01.wav</ShortName>
							<Path>SFX\Weapons\K20_Wales_Sword\sfx_wpn_k20_trail_start_a_01_7FA8D501.wem</Path>
						</File>
						<File Id="362509630" Language="SFX">
							<ShortName>Weapons\K20_Wales_Sword\sfx_wpn_k20_trail_start_b_02.wav</ShortName>
							<Path>SFX\Weapons\K20_Wales_Sword\sfx_wpn_k20_trail_start_b_02_7FA8D501.wem</Path>
						</File>
						<File Id="588597432" Language="SFX">
							<ShortName>Weapons\K20_Wales_Sword\sfx_wpn_k20_trail_start_b_01.wav</ShortName>
							<Path>SFX\Weapons\K20_Wales_Sword\sfx_wpn_k20_trail_start_b_01_7FA8D501.wem</Path>
						</File>
						<File Id="982964762" Language="SFX">
							<ShortName>Weapons\K20_Wales_Sword\sfx_wpn_k20_trail_start_b_03.wav</ShortName>
							<Path>SFX\Weapons\K20_Wales_Sword\sfx_wpn_k20_trail_start_b_03_7FA8D501.wem</Path>
						</File>
					</IncludedMemoryFiles>
					<AuxBusSends>
						<AuxBus Id="286574509" Name="MENU_KLR_00_COMMON" ObjectPath="\Master-Mixer Hierarchy\Default Work Unit\Master Audio Bus\SFX\MENU\MENU_OBJECT\MENU_KILLER\MENU_KLR_00_COMMON" GUID="{E64B324D-8F4B-4D04-AAC1-282FD4D9B765}"/>
					</AuxBusSends>
				</Event>
				<Event Id="1516627620" Name="AudioEvent_K20_WPN_Default_Sword_Arm" ObjectPath="\Events\CHARACTER\KILLER\KLR_20_Wales\K20_WEAPON\AudioEvent_K20_WPN_Default_Sword_Arm" GUID="{54C0F68E-7BDC-4DF2-A551-50CD4E9671A6}" MaxAttenuation="1250.000000" DurationType="OneShot" DurationMin="1.006968" DurationMax="1.006968">
					<IncludedMemoryFiles>
						<File Id="243150391" Language="SFX">
							<ShortName>Weapons\K20_Wales_Sword\sfx_wpn_k20_arm_01.wav</ShortName>
							<Path>SFX\Weapons\K20_Wales_Sword\sfx_wpn_k20_arm_01_A6D11F5D.wem</Path>
						</File>
					</IncludedMemoryFiles>
					<AuxBusSends>
						<AuxBus Id="286574509" Name="MENU_KLR_00_COMMON" ObjectPath="\Master-Mixer Hierarchy\Default Work Unit\Master Audio Bus\SFX\MENU\MENU_OBJECT\MENU_KILLER\MENU_KLR_00_COMMON" GUID="{E64B324D-8F4B-4D04-AAC1-282FD4D9B765}"/>
					</AuxBusSends>
				</Event>
				<Event Id="4250957074" Name="AudioEvent_K20_WPN_Default_Sword_Attack" ObjectPath="\Events\CHARACTER\KILLER\KLR_20_Wales\K20_WEAPON\AudioEvent_K20_WPN_Default_Sword_Attack" GUID="{D97C90D1-EF8D-4D8A-9308-4D88ED3E4A57}" MaxAttenuation="1900.000000" DurationType="OneShot" DurationMin="0.705470" DurationMax="0.880259">
					<IncludedMemoryFiles>
						<File Id="99661307" Language="SFX">
							<ShortName>Weapons\K20_Wales_Sword\sfx_wpm_k20_wales_attack_B_01.wav</ShortName>
							<Path>SFX\Weapons\K20_Wales_Sword\sfx_wpm_k20_wales_attack_B_01_7FA8D501.wem</Path>
						</File>
						<File Id="372517459" Language="SFX">
							<ShortName>Weapons\K20_Wales_Sword\sfx_wpm_k20_wales_attack_a_02.wav</ShortName>
							<Path>SFX\Weapons\K20_Wales_Sword\sfx_wpm_k20_wales_attack_a_02_7FA8D501.wem</Path>
						</File>
						<File Id="406938301" Language="SFX">
							<ShortName>Weapons\K20_Wales_Sword\sfx_wpm_k20_wales_attack_a_01.wav</ShortName>
							<Path>SFX\Weapons\K20_Wales_Sword\sfx_wpm_k20_wales_attack_a_01_7FA8D501.wem</Path>
						</File>
						<File Id="902108222" Language="SFX">
							<ShortName>Weapons\K20_Wales_Sword\sfx_wpm_k20_wales_attack_a_03.wav</ShortName>
							<Path>SFX\Weapons\K20_Wales_Sword\sfx_wpm_k20_wales_attack_a_03_7FA8D501.wem</Path>
						</File>
					</IncludedMemoryFiles>
					<AuxBusSends>
						<AuxBus Id="286574509" Name="MENU_KLR_00_COMMON" ObjectPath="\Master-Mixer Hierarchy\Default Work Unit\Master Audio Bus\SFX\MENU\MENU_OBJECT\MENU_KILLER\MENU_KLR_00_COMMON" GUID="{E64B324D-8F4B-4D04-AAC1-282FD4D9B765}"/>
					</AuxBusSends>
				</Event>
				<Event Id="2502695053" Name="AudioEvent_K20_WPN_Default_Sword_Clean" ObjectPath="\Events\CHARACTER\KILLER\KLR_20_Wales\K20_WEAPON\AudioEvent_K20_WPN_Default_Sword_Clean" GUID="{4D920439-F643-4737-AF72-8A02E6171A34}" MaxAttenuation="850.000000" DurationType="OneShot" DurationMin="0.660719" DurationMax="0.660719">
					<IncludedMemoryFiles>
						<File Id="182088732" Language="SFX">
							<ShortName>Weapons\K20_Wales_Sword\sfx_wpn_k20_wales_clean_01.wav</ShortName>
							<Path>SFX\Weapons\K20_Wales_Sword\sfx_wpn_k20_wales_clean_01_7FA8D501.wem</Path>
						</File>
					</IncludedMemoryFiles>
					<AuxBusSends>
						<AuxBus Id="286574509" Name="MENU_KLR_00_COMMON" ObjectPath="\Master-Mixer Hierarchy\Default Work Unit\Master Audio Bus\SFX\MENU\MENU_OBJECT\MENU_KILLER\MENU_KLR_00_COMMON" GUID="{E64B324D-8F4B-4D04-AAC1-282FD4D9B765}"/>
					</AuxBusSends>
				</Event>
				<Event Id="2901083312" Name="AudioEvent_K20_WPN_Default_Sword_Impact" ObjectPath="\Events\CHARACTER\KILLER\KLR_20_Wales\K20_WEAPON\AudioEvent_K20_WPN_Default_Sword_Impact" GUID="{3BB5637A-05D1-4420-A08A-7403B52F8555}" MaxAttenuation="1700.000000" DurationType="OneShot" DurationMin="0.363833" DurationMax="0.880000">
					<IncludedMemoryFiles>
						<File Id="223674030" Language="SFX">
							<ShortName>Weapons\K20_Wales_Sword\sfx_wpn_ukraine_impact_hit_soft_01.wav</ShortName>
							<Path>SFX\Weapons\K20_Wales_Sword\sfx_wpn_ukraine_impact_hit_soft_01_7FA8D501.wem</Path>
						</File>
						<File Id="246513855" Language="SFX">
							<ShortName>Weapons\K20_Wales_Sword\sfx_wpn_ukraine_impact_hit_02.wav</ShortName>
							<Path>SFX\Weapons\K20_Wales_Sword\sfx_wpn_ukraine_impact_hit_02_7FA8D501.wem</Path>
						</File>
						<File Id="685449009" Language="SFX">
							<ShortName>Weapons\K20_Wales_Sword\sfx_wpn_ukraine_impact_hit_01.wav</ShortName>
							<Path>SFX\Weapons\K20_Wales_Sword\sfx_wpn_ukraine_impact_hit_01_7FA8D501.wem</Path>
						</File>
						<File Id="882878402" Language="SFX">
							<ShortName>Weapons\K20_Wales_Sword\sfx_wpn_ukraine_impact_hit_03.wav</ShortName>
							<Path>SFX\Weapons\K20_Wales_Sword\sfx_wpn_ukraine_impact_hit_03_7FA8D501.wem</Path>
						</File>
						<File Id="907544737" Language="SFX">
							<ShortName>Weapons\K20_Wales_Sword\sfx_wpn_ukraine_impact_hit_soft_02.wav</ShortName>
							<Path>SFX\Weapons\K20_Wales_Sword\sfx_wpn_ukraine_impact_hit_soft_02_7FA8D501.wem</Path>
						</File>
						<File Id="1063116323" Language="SFX">
							<ShortName>Weapons\K20_Wales_Sword\sfx_wpn_ukraine_impact_hit_soft_03.wav</ShortName>
							<Path>SFX\Weapons\K20_Wales_Sword\sfx_wpn_ukraine_impact_hit_soft_03_7FA8D501.wem</Path>
						</File>
					</IncludedMemoryFiles>
					<DefaultSwitchValue>{82BAB65C-92F7-4F63-990C-4F5495B4979B}</DefaultSwitchValue>
					<SwitchContainers>
						<SwitchContainer SwitchValue="{2792490C-9C7E-402A-B630-E1AEE10B67B0}">
							<Media>
								<File Id="685449009"/>
								<File Id="246513855"/>
								<File Id="882878402"/>
							</Media>
						</SwitchContainer>
						<SwitchContainer SwitchValue="{1974DF19-3EAC-4718-94A9-7C7895513BA6}">
							<Media>
								<File Id="223674030"/>
								<File Id="907544737"/>
								<File Id="1063116323"/>
							</Media>
						</SwitchContainer>
					</SwitchContainers>
					<AuxBusSends>
						<AuxBus Id="286574509" Name="MENU_KLR_00_COMMON" ObjectPath="\Master-Mixer Hierarchy\Default Work Unit\Master Audio Bus\SFX\MENU\MENU_OBJECT\MENU_KILLER\MENU_KLR_00_COMMON" GUID="{E64B324D-8F4B-4D04-AAC1-282FD4D9B765}"/>
					</AuxBusSends>
				</Event>
				<Event Id="4265775017" Name="AudioEvent_K20_WPN_Default_Sword_PullOut" ObjectPath="\Events\CHARACTER\KILLER\KLR_20_Wales\K20_WEAPON\AudioEvent_K20_WPN_Default_Sword_PullOut" GUID="{3E15A478-778F-4CFE-B2D5-104CF7242885}" MaxAttenuation="1700.000000" DurationType="OneShot" DurationMin="1.230913" DurationMax="1.230913">
					<IncludedMemoryFiles>
						<File Id="193381019" Language="SFX">
							<ShortName>Weapons\K20_Wales_Sword\sfx_wpn_k20_wales_pullout_01.wav</ShortName>
							<Path>SFX\Weapons\K20_Wales_Sword\sfx_wpn_k20_wales_pullout_01_7FA8D501.wem</Path>
						</File>
					</IncludedMemoryFiles>
					<AuxBusSends>
						<AuxBus Id="286574509" Name="MENU_KLR_00_COMMON" ObjectPath="\Master-Mixer Hierarchy\Default Work Unit\Master Audio Bus\SFX\MENU\MENU_OBJECT\MENU_KILLER\MENU_KLR_00_COMMON" GUID="{E64B324D-8F4B-4D04-AAC1-282FD4D9B765}"/>
					</AuxBusSends>
				</Event>
				<Event Id="4075838616" Name="AudioEvent_Killer_Wales_Grunt_Attack" ObjectPath="\Events\CHARACTER\KILLER\KLR_20_Wales\K20_GRUNT\AudioEvent_Killer_Wales_Grunt_Attack" GUID="{6666EB7B-4253-471C-B56D-693AAA5E6128}" MaxAttenuation="1900.000000" DurationType="OneShot" DurationMin="0.801623" DurationMax="1.440167">
					<IncludedMemoryFiles>
						<File Id="54568869" Language="SFX">
							<ShortName>Characters\Killer_Wales\sfx_killer_wales_grunt_a_01.wav</ShortName>
							<Path>SFX\Characters\Killer_Wales\sfx_killer_wales_grunt_a_01_7FA8D501.wem</Path>
						</File>
						<File Id="363062404" Language="SFX">
							<ShortName>Characters\Killer_Wales\sfx_killer_wales_grunt_a_03.wav</ShortName>
							<Path>SFX\Characters\Killer_Wales\sfx_killer_wales_grunt_a_03_7FA8D501.wem</Path>
						</File>
						<File Id="491115095" Language="SFX">
							<ShortName>Characters\Killer_Wales\sfx_killer_wales_grunt_a_05.wav</ShortName>
							<Path>SFX\Characters\Killer_Wales\sfx_killer_wales_grunt_a_05_7FA8D501.wem</Path>
						</File>
						<File Id="781073151" Language="SFX">
							<ShortName>Characters\Killer_Wales\sfx_killer_wales_grunt_a_02.wav</ShortName>
							<Path>SFX\Characters\Killer_Wales\sfx_killer_wales_grunt_a_02_7FA8D501.wem</Path>
						</File>
						<File Id="883796864" Language="SFX">
							<ShortName>Characters\Killer_Wales\sfx_killer_wales_grunt_a_04.wav</ShortName>
							<Path>SFX\Characters\Killer_Wales\sfx_killer_wales_grunt_a_04_7FA8D501.wem</Path>
						</File>
					</IncludedMemoryFiles>
					<AuxBusSends>
						<AuxBus Id="286574509" Name="MENU_KLR_00_COMMON" ObjectPath="\Master-Mixer Hierarchy\Default Work Unit\Master Audio Bus\SFX\MENU\MENU_OBJECT\MENU_KILLER\MENU_KLR_00_COMMON" GUID="{E64B324D-8F4B-4D04-AAC1-282FD4D9B765}"/>
					</AuxBusSends>
				</Event>
				<Event Id="2561506111" Name="AudioEvent_Killer_Wales_Grunt_Hurt" ObjectPath="\Events\CHARACTER\KILLER\KLR_20_Wales\K20_GRUNT\AudioEvent_Killer_Wales_Grunt_Hurt" GUID="{A7F53CE6-B087-4096-ABCB-79745242E300}" MaxAttenuation="1900.000000" DurationType="OneShot" DurationMin="1.451571" DurationMax="2.217333">
					<IncludedMemoryFiles>
						<File Id="139056690" Language="SFX">
							<ShortName>Characters\Killer_Wales\sfx_k20_wales_stunned_b_02.wav</ShortName>
							<Path>SFX\Characters\Killer_Wales\sfx_k20_wales_stunned_b_02_7FA8D501.wem</Path>
						</File>
						<File Id="306446179" Language="SFX">
							<ShortName>Characters\Killer_Wales\sfx_k20_wales_stunned_b_01.wav</ShortName>
							<Path>SFX\Characters\Killer_Wales\sfx_k20_wales_stunned_b_01_7FA8D501.wem</Path>
						</File>
						<File Id="739768844" Language="SFX">
							<ShortName>Characters\Killer_Wales\sfx_k20_wales_stunned_b_05.wav</ShortName>
							<Path>SFX\Characters\Killer_Wales\sfx_k20_wales_stunned_b_05_7FA8D501.wem</Path>
						</File>
						<File Id="867125055" Language="SFX">
							<ShortName>Characters\Killer_Wales\sfx_k20_wales_stunned_b_03.wav</ShortName>
							<Path>SFX\Characters\Killer_Wales\sfx_k20_wales_stunned_b_03_7FA8D501.wem</Path>
						</File>
						<File Id="924958312" Language="SFX">
							<ShortName>Characters\Killer_Wales\sfx_k20_wales_stunned_b_04.wav</ShortName>
							<Path>SFX\Characters\Killer_Wales\sfx_k20_wales_stunned_b_04_7FA8D501.wem</Path>
						</File>
					</IncludedMemoryFiles>
					<AuxBusSends>
						<AuxBus Id="286574509" Name="MENU_KLR_00_COMMON" ObjectPath="\Master-Mixer Hierarchy\Default Work Unit\Master Audio Bus\SFX\MENU\MENU_OBJECT\MENU_KILLER\MENU_KLR_00_COMMON" GUID="{E64B324D-8F4B-4D04-AAC1-282FD4D9B765}"/>
					</AuxBusSends>
				</Event>
				<Event Id="936256922" Name="AudioEvent_Killer_Wales_Grunt_Power_Start" ObjectPath="\Events\CHARACTER\KILLER\KLR_20_Wales\K20_GRUNT\AudioEvent_Killer_Wales_Grunt_Power_Start" GUID="{89B166D7-B37D-454F-984E-EF90E072034B}" MaxAttenuation="1900.000000" DurationType="OneShot" DurationMin="0.801623" DurationMax="1.440167">
					<IncludedMemoryFiles>
						<File Id="54568869" Language="SFX">
							<ShortName>Characters\Killer_Wales\sfx_killer_wales_grunt_a_01.wav</ShortName>
							<Path>SFX\Characters\Killer_Wales\sfx_killer_wales_grunt_a_01_7FA8D501.wem</Path>
						</File>
						<File Id="363062404" Language="SFX">
							<ShortName>Characters\Killer_Wales\sfx_killer_wales_grunt_a_03.wav</ShortName>
							<Path>SFX\Characters\Killer_Wales\sfx_killer_wales_grunt_a_03_7FA8D501.wem</Path>
						</File>
						<File Id="491115095" Language="SFX">
							<ShortName>Characters\Killer_Wales\sfx_killer_wales_grunt_a_05.wav</ShortName>
							<Path>SFX\Characters\Killer_Wales\sfx_killer_wales_grunt_a_05_7FA8D501.wem</Path>
						</File>
						<File Id="781073151" Language="SFX">
							<ShortName>Characters\Killer_Wales\sfx_killer_wales_grunt_a_02.wav</ShortName>
							<Path>SFX\Characters\Killer_Wales\sfx_killer_wales_grunt_a_02_7FA8D501.wem</Path>
						</File>
						<File Id="883796864" Language="SFX">
							<ShortName>Characters\Killer_Wales\sfx_killer_wales_grunt_a_04.wav</ShortName>
							<Path>SFX\Characters\Killer_Wales\sfx_killer_wales_grunt_a_04_7FA8D501.wem</Path>
						</File>
					</IncludedMemoryFiles>
					<AuxBusSends>
						<AuxBus Id="286574509" Name="MENU_KLR_00_COMMON" ObjectPath="\Master-Mixer Hierarchy\Default Work Unit\Master Audio Bus\SFX\MENU\MENU_OBJECT\MENU_KILLER\MENU_KLR_00_COMMON" GUID="{E64B324D-8F4B-4D04-AAC1-282FD4D9B765}"/>
					</AuxBusSends>
				</Event>
				<Event Id="27456167" Name="AudioEvent_Killer_Wales_Sepc_Mori_Barbedwire_Close" ObjectPath="\Events\CHARACTER\KILLER\KLR_20_Wales\K20_SPECIFIC\AudioEvent_Killer_Wales_Sepc_Mori_Barbedwire_Close" GUID="{CED3A071-BDFB-46EB-9AC3-849BD9DA4188}" MaxAttenuation="1700.000000" DurationType="OneShot" DurationMin="1.534875" DurationMax="1.534875">
					<IncludedMemoryFiles>
						<File Id="484239117" Language="SFX">
							<ShortName>Characters\Killer_Wales\sfx_k20_wales_mori_barbedwire_close_01.wav</ShortName>
							<Path>SFX\Characters\Killer_Wales\sfx_k20_wales_mori_barbedwire_close_01_7FA8D501.wem</Path>
						</File>
					</IncludedMemoryFiles>
					<AuxBusSends>
						<AuxBus Id="286574509" Name="MENU_KLR_00_COMMON" ObjectPath="\Master-Mixer Hierarchy\Default Work Unit\Master Audio Bus\SFX\MENU\MENU_OBJECT\MENU_KILLER\MENU_KLR_00_COMMON" GUID="{E64B324D-8F4B-4D04-AAC1-282FD4D9B765}"/>
					</AuxBusSends>
				</Event>
				<Event Id="951869265" Name="AudioEvent_Killer_Wales_Sepc_Mori_Barbedwire_Open" ObjectPath="\Events\CHARACTER\KILLER\KLR_20_Wales\K20_SPECIFIC\AudioEvent_Killer_Wales_Sepc_Mori_Barbedwire_Open" GUID="{A01E79F0-EC5B-47A5-8CC7-F787B838AF8D}" MaxAttenuation="1700.000000" DurationType="OneShot" DurationMin="0.800812" DurationMax="0.800812">
					<IncludedMemoryFiles>
						<File Id="114255427" Language="SFX">
							<ShortName>Characters\Killer_Wales\sfx_k20_wales_mori_barbedwire_open_01.wav</ShortName>
							<Path>SFX\Characters\Killer_Wales\sfx_k20_wales_mori_barbedwire_open_01_7FA8D501.wem</Path>
						</File>
					</IncludedMemoryFiles>
					<AuxBusSends>
						<AuxBus Id="286574509" Name="MENU_KLR_00_COMMON" ObjectPath="\Master-Mixer Hierarchy\Default Work Unit\Master Audio Bus\SFX\MENU\MENU_OBJECT\MENU_KILLER\MENU_KLR_00_COMMON" GUID="{E64B324D-8F4B-4D04-AAC1-282FD4D9B765}"/>
					</AuxBusSends>
				</Event>
				<Event Id="1283756919" Name="AudioEvent_Killer_Wales_Sepc_Mori_MetalBeam_Spawn" ObjectPath="\Events\CHARACTER\KILLER\KLR_20_Wales\K20_SPECIFIC\AudioEvent_Killer_Wales_Sepc_Mori_MetalBeam_Spawn" GUID="{A358A6F2-CAF0-453A-BA32-31290E6F4CFC}" MaxAttenuation="1700.000000" DurationType="OneShot" DurationMin="1.868542" DurationMax="1.868542">
					<IncludedMemoryFiles>
						<File Id="824586549" Language="SFX">
							<ShortName>Characters\Killer_Wales\sfx_k20_wales_mori_metalbeam_spawn_01.wav</ShortName>
							<Path>SFX\Characters\Killer_Wales\sfx_k20_wales_mori_metalbeam_spawn_01_7FA8D501.wem</Path>
						</File>
					</IncludedMemoryFiles>
					<AuxBusSends>
						<AuxBus Id="286574509" Name="MENU_KLR_00_COMMON" ObjectPath="\Master-Mixer Hierarchy\Default Work Unit\Master Audio Bus\SFX\MENU\MENU_OBJECT\MENU_KILLER\MENU_KLR_00_COMMON" GUID="{E64B324D-8F4B-4D04-AAC1-282FD4D9B765}"/>
					</AuxBusSends>
				</Event>
				<Event Id="4257343976" Name="AudioEvent_Killer_Wales_Sword_Friction_Stop" ObjectPath="\Events\CHARACTER\KILLER\KLR_20_Wales\K20_SPECIFIC\AudioEvent_Killer_Wales_Sword_Friction_Stop" GUID="{FEB79C1D-F2D0-4CF4-9A19-D502DCEC9687}" MaxAttenuation="0.000000" DurationType="OneShot" DurationMin="0.000000" DurationMax="0.000000"/>
				<Event Id="3415432224" Name="AudioEvent_KLR_20_Status_Start" ObjectPath="\Events\CHARACTER\KILLER\KLR_20_Wales\K20_STATUS\AudioEvent_KLR_20_Status_Start" GUID="{0D0362D7-64B9-41DB-A6A9-64066714C408}" MaxAttenuation="1900.000000" DurationType="Infinite">
					<IncludedMemoryFiles>
						<File Id="114767618" Language="SFX">
							<ShortName>Characters\Killer_Wales\sfx_killer_wales_status_breath_out_08.wav</ShortName>
							<Path>SFX\Characters\Killer_Wales\sfx_killer_wales_status_breath_out_08_7FA8D501.wem</Path>
						</File>
						<File Id="148852574" Language="SFX">
							<ShortName>Characters\Killer_Wales\sfx_killer_wales_status_breath_out_01.wav</ShortName>
							<Path>SFX\Characters\Killer_Wales\sfx_killer_wales_status_breath_out_01_7FA8D501.wem</Path>
						</File>
						<File Id="197431594" Language="SFX">
							<ShortName>Characters\Killer_Wales\sfx_killer_wales_status_breath_in_01.wav</ShortName>
							<Path>SFX\Characters\Killer_Wales\sfx_killer_wales_status_breath_in_01_7FA8D501.wem</Path>
						</File>
						<File Id="226875670" Language="SFX">
							<ShortName>Characters\Killer_Wales\sfx_killer_wales_status_breath_out_06.wav</ShortName>
							<Path>SFX\Characters\Killer_Wales\sfx_killer_wales_status_breath_out_06_7FA8D501.wem</Path>
						</File>
						<File Id="606793767" Language="SFX">
							<ShortName>Characters\Killer_Wales\sfx_killer_wales_status_breath_in_08.wav</ShortName>
							<Path>SFX\Characters\Killer_Wales\sfx_killer_wales_status_breath_in_08_7FA8D501.wem</Path>
						</File>
						<File Id="693120686" Language="SFX">
							<ShortName>Characters\Killer_Wales\sfx_killer_wales_status_breath_out_05.wav</ShortName>
							<Path>SFX\Characters\Killer_Wales\sfx_killer_wales_status_breath_out_05_7FA8D501.wem</Path>
						</File>
						<File Id="803646609" Language="SFX">
							<ShortName>Characters\Killer_Wales\sfx_killer_wales_status_breath_in_02.wav</ShortName>
							<Path>SFX\Characters\Killer_Wales\sfx_killer_wales_status_breath_in_02_7FA8D501.wem</Path>
						</File>
						<File Id="820381585" Language="SFX">
							<ShortName>Characters\Killer_Wales\sfx_killer_wales_status_breath_in_04.wav</ShortName>
							<Path>SFX\Characters\Killer_Wales\sfx_killer_wales_status_breath_in_04_7FA8D501.wem</Path>
						</File>
						<File Id="884779177" Language="SFX">
							<ShortName>Characters\Killer_Wales\sfx_killer_wales_status_breath_out_03.wav</ShortName>
							<Path>SFX\Characters\Killer_Wales\sfx_killer_wales_status_breath_out_03_7FA8D501.wem</Path>
						</File>
						<File Id="886454225" Language="SFX">
							<ShortName>Characters\Killer_Wales\sfx_killer_wales_status_breath_in_03.wav</ShortName>
							<Path>SFX\Characters\Killer_Wales\sfx_killer_wales_status_breath_in_03_7FA8D501.wem</Path>
						</File>
						<File Id="900099185" Language="SFX">
							<ShortName>Characters\Killer_Wales\sfx_killer_wales_status_breath_out_07.wav</ShortName>
							<Path>SFX\Characters\Killer_Wales\sfx_killer_wales_status_breath_out_07_7FA8D501.wem</Path>
						</File>
						<File Id="910758931" Language="SFX">
							<ShortName>Characters\Killer_Wales\sfx_killer_wales_status_breath_in_07.wav</ShortName>
							<Path>SFX\Characters\Killer_Wales\sfx_killer_wales_status_breath_in_07_7FA8D501.wem</Path>
						</File>
						<File Id="927015364" Language="SFX">
							<ShortName>Characters\Killer_Wales\sfx_killer_wales_status_breath_in_09.wav</ShortName>
							<Path>SFX\Characters\Killer_Wales\sfx_killer_wales_status_breath_in_09_7FA8D501.wem</Path>
						</File>
						<File Id="952891751" Language="SFX">
							<ShortName>Characters\Killer_Wales\sfx_killer_wales_status_breath_out_02.wav</ShortName>
							<Path>SFX\Characters\Killer_Wales\sfx_killer_wales_status_breath_out_02_7FA8D501.wem</Path>
						</File>
						<File Id="1016849159" Language="SFX">
							<ShortName>Characters\Killer_Wales\sfx_killer_wales_status_breath_in_05.wav</ShortName>
							<Path>SFX\Characters\Killer_Wales\sfx_killer_wales_status_breath_in_05_7FA8D501.wem</Path>
						</File>
						<File Id="1048509918" Language="SFX">
							<ShortName>Characters\Killer_Wales\sfx_killer_wales_status_breath_out_04.wav</ShortName>
							<Path>SFX\Characters\Killer_Wales\sfx_killer_wales_status_breath_out_04_7FA8D501.wem</Path>
						</File>
						<File Id="1061147700" Language="SFX">
							<ShortName>Characters\Killer_Wales\sfx_killer_wales_status_breath_in_06.wav</ShortName>
							<Path>SFX\Characters\Killer_Wales\sfx_killer_wales_status_breath_in_06_7FA8D501.wem</Path>
						</File>
					</IncludedMemoryFiles>
					<AuxBusSends>
						<AuxBus Id="286574509" Name="MENU_KLR_00_COMMON" ObjectPath="\Master-Mixer Hierarchy\Default Work Unit\Master Audio Bus\SFX\MENU\MENU_OBJECT\MENU_KILLER\MENU_KLR_00_COMMON" GUID="{E64B324D-8F4B-4D04-AAC1-282FD4D9B765}"/>
					</AuxBusSends>
				</Event>
				<Event Id="133115212" Name="AudioEvent_KLR_20_Status_Stop" ObjectPath="\Events\CHARACTER\KILLER\KLR_20_Wales\K20_STATUS\AudioEvent_KLR_20_Status_Stop" GUID="{F5A9F6CB-4680-49AB-A82E-001E2B255469}" MaxAttenuation="0.000000" DurationType="OneShot" DurationMin="0.000000" DurationMax="0.000000"/>
				<Event Id="2962243787" Name="AudioEvent_PWR_Wales_Agony_BarbedWire_Spawn" ObjectPath="\Events\CHARACTER\KILLER\KLR_20_Wales\K20_POWER\AudioEvent_PWR_Wales_Agony_BarbedWire_Spawn" GUID="{F5D268BE-FE1E-4C6B-8D2D-976B9DAC5D4F}" MaxAttenuation="850.000000" DurationType="OneShot" DurationMin="0.388417" DurationMax="0.844729">
					<IncludedMemoryFiles>
						<File Id="40001080" Language="SFX">
							<ShortName>Powers\PWR_20_Wales\sfx_pwr_k20_agony_barbedwire_spawn_single_12.wav</ShortName>
							<Path>SFX\Powers\PWR_20_Wales\sfx_pwr_k20_agony_barbedwire_spawn_single_12_7FA8D501.wem</Path>
						</File>
						<File Id="113543388" Language="SFX">
							<ShortName>Powers\PWR_20_Wales\sfx_pwr_k20_agony_barbedwire_spawn_single_04.wav</ShortName>
							<Path>SFX\Powers\PWR_20_Wales\sfx_pwr_k20_agony_barbedwire_spawn_single_04_7FA8D501.wem</Path>
						</File>
						<File Id="114795935" Language="SFX">
							<ShortName>Powers\PWR_20_Wales\sfx_pwr_k20_agony_barbedwire_spawn_single_01.wav</ShortName>
							<Path>SFX\Powers\PWR_20_Wales\sfx_pwr_k20_agony_barbedwire_spawn_single_01_7FA8D501.wem</Path>
						</File>
						<File Id="117239976" Language="SFX">
							<ShortName>Powers\PWR_20_Wales\sfx_pwr_k20_agony_barbedwire_spawn_single_08.wav</ShortName>
							<Path>SFX\Powers\PWR_20_Wales\sfx_pwr_k20_agony_barbedwire_spawn_single_08_7FA8D501.wem</Path>
						</File>
						<File Id="128840165" Language="SFX">
							<ShortName>Powers\PWR_20_Wales\sfx_pwr_k20_agony_barbedwire_spawn_single_13.wav</ShortName>
							<Path>SFX\Powers\PWR_20_Wales\sfx_pwr_k20_agony_barbedwire_spawn_single_13_7FA8D501.wem</Path>
						</File>
						<File Id="169431548" Language="SFX">
							<ShortName>Powers\PWR_20_Wales\sfx_pwr_k20_agony_barbedwire_spawn_single_17.wav</ShortName>
							<Path>SFX\Powers\PWR_20_Wales\sfx_pwr_k20_agony_barbedwire_spawn_single_17_7FA8D501.wem</Path>
						</File>
						<File Id="188530523" Language="SFX">
							<ShortName>Powers\PWR_20_Wales\sfx_pwr_k20_agony_barbedwire_spawn_single_14.wav</ShortName>
							<Path>SFX\Powers\PWR_20_Wales\sfx_pwr_k20_agony_barbedwire_spawn_single_14_7FA8D501.wem</Path>
						</File>
						<File Id="330841894" Language="SFX">
							<ShortName>Powers\PWR_20_Wales\sfx_pwr_k20_agony_barbedwire_spawn_single_10.wav</ShortName>
							<Path>SFX\Powers\PWR_20_Wales\sfx_pwr_k20_agony_barbedwire_spawn_single_10_7FA8D501.wem</Path>
						</File>
						<File Id="545010480" Language="SFX">
							<ShortName>Powers\PWR_20_Wales\sfx_pwr_k20_agony_barbedwire_spawn_single_07.wav</ShortName>
							<Path>SFX\Powers\PWR_20_Wales\sfx_pwr_k20_agony_barbedwire_spawn_single_07_7FA8D501.wem</Path>
						</File>
						<File Id="631463066" Language="SFX">
							<ShortName>Powers\PWR_20_Wales\sfx_pwr_k20_agony_barbedwire_spawn_single_09.wav</ShortName>
							<Path>SFX\Powers\PWR_20_Wales\sfx_pwr_k20_agony_barbedwire_spawn_single_09_7FA8D501.wem</Path>
						</File>
						<File Id="681348560" Language="SFX">
							<ShortName>Powers\PWR_20_Wales\sfx_pwr_k20_agony_barbedwire_spawn_single_06.wav</ShortName>
							<Path>SFX\Powers\PWR_20_Wales\sfx_pwr_k20_agony_barbedwire_spawn_single_06_7FA8D501.wem</Path>
						</File>
						<File Id="687833449" Language="SFX">
							<ShortName>Powers\PWR_20_Wales\sfx_pwr_k20_agony_barbedwire_spawn_single_11.wav</ShortName>
							<Path>SFX\Powers\PWR_20_Wales\sfx_pwr_k20_agony_barbedwire_spawn_single_11_7FA8D501.wem</Path>
						</File>
						<File Id="796279462" Language="SFX">
							<ShortName>Powers\PWR_20_Wales\sfx_pwr_k20_agony_barbedwire_spawn_single_15.wav</ShortName>
							<Path>SFX\Powers\PWR_20_Wales\sfx_pwr_k20_agony_barbedwire_spawn_single_15_7FA8D501.wem</Path>
						</File>
						<File Id="810937022" Language="SFX">
							<ShortName>Powers\PWR_20_Wales\sfx_pwr_k20_agony_barbedwire_spawn_single_02.wav</ShortName>
							<Path>SFX\Powers\PWR_20_Wales\sfx_pwr_k20_agony_barbedwire_spawn_single_02_7FA8D501.wem</Path>
						</File>
						<File Id="973325910" Language="SFX">
							<ShortName>Powers\PWR_20_Wales\sfx_pwr_k20_agony_barbedwire_spawn_single_16.wav</ShortName>
							<Path>SFX\Powers\PWR_20_Wales\sfx_pwr_k20_agony_barbedwire_spawn_single_16_7FA8D501.wem</Path>
						</File>
						<File Id="1046483499" Language="SFX">
							<ShortName>Powers\PWR_20_Wales\sfx_pwr_k20_agony_barbedwire_spawn_single_05.wav</ShortName>
							<Path>SFX\Powers\PWR_20_Wales\sfx_pwr_k20_agony_barbedwire_spawn_single_05_7FA8D501.wem</Path>
						</File>
						<File Id="1059060445" Language="SFX">
							<ShortName>Powers\PWR_20_Wales\sfx_pwr_k20_agony_barbedwire_spawn_single_03.wav</ShortName>
							<Path>SFX\Powers\PWR_20_Wales\sfx_pwr_k20_agony_barbedwire_spawn_single_03_7FA8D501.wem</Path>
						</File>
					</IncludedMemoryFiles>
				</Event>
				<Event Id="632324500" Name="AudioEvent_PWR_Wales_Agony_Start" ObjectPath="\Events\CHARACTER\KILLER\KLR_20_Wales\K20_POWER\AudioEvent_PWR_Wales_Agony_Start" GUID="{EBEA4411-C27A-4AB6-A910-7599126F88FD}" DurationType="OneShot" DurationMin="4.703945" DurationMax="5.955035">
					<IncludedMemoryFiles>
						<File Id="217916416" Language="SFX">
							<ShortName>Powers\PWR_20_Wales\sfx_power_k20_agony_start_a_03.wav</ShortName>
							<Path>SFX\Powers\PWR_20_Wales\sfx_power_k20_agony_start_a_03_7FA8D501.wem</Path>
						</File>
						<File Id="769872597" Language="SFX">
							<ShortName>Powers\PWR_20_Wales\sfx_power_k20_agony_start_a_01.wav</ShortName>
							<Path>SFX\Powers\PWR_20_Wales\sfx_power_k20_agony_start_a_01_7FA8D501.wem</Path>
						</File>
						<File Id="1062394367" Language="SFX">
							<ShortName>Powers\PWR_20_Wales\sfx_power_k20_agony_start_a_02.wav</ShortName>
							<Path>SFX\Powers\PWR_20_Wales\sfx_power_k20_agony_start_a_02_7FA8D501.wem</Path>
						</File>
					</IncludedMemoryFiles>
				</Event>
				<Event Id="2905730163" Name="AudioEvent_PWR_Wales_Agony_Trail_Crossing" ObjectPath="\Events\CHARACTER\KILLER\KLR_20_Wales\K20_POWER\AudioEvent_PWR_Wales_Agony_Trail_Crossing" GUID="{24D5BA5A-C103-4E05-BCD5-042F66BA836D}" DurationType="OneShot" DurationMin="8.469334" DurationMax="9.098666">
					<IncludedMemoryFiles>
						<File Id="186891162" Language="SFX">
							<ShortName>Powers\PWR_20_Wales\sfx_power_k20_agony_start_b_02.wav</ShortName>
							<Path>SFX\Powers\PWR_20_Wales\sfx_power_k20_agony_start_b_02_7FA8D501.wem</Path>
						</File>
						<File Id="289332045" Language="SFX">
							<ShortName>Powers\PWR_20_Wales\sfx_power_k20_agony_start_b_01.wav</ShortName>
							<Path>SFX\Powers\PWR_20_Wales\sfx_power_k20_agony_start_b_01_7FA8D501.wem</Path>
						</File>
						<File Id="1019748496" Language="SFX">
							<ShortName>Powers\PWR_20_Wales\sfx_power_k20_agony_start_b_03.wav</ShortName>
							<Path>SFX\Powers\PWR_20_Wales\sfx_power_k20_agony_start_b_03_7FA8D501.wem</Path>
						</File>
					</IncludedMemoryFiles>
				</Event>
				<Event Id="864822439" Name="AudioEvent_PWR_Wales_Attack2_Hit_Confirmation" ObjectPath="\Events\CHARACTER\KILLER\KLR_20_Wales\K20_POWER\AudioEvent_PWR_Wales_Attack2_Hit_Confirmation" GUID="{660929A8-A590-4B33-B816-DD17CD121470}" DurationType="OneShot" DurationMin="2.846396" DurationMax="2.846396">
					<IncludedMemoryFiles>
						<File Id="255254260" Language="SFX">
							<ShortName>Powers\PWR_20_Wales\sfx_power_k20_attack2_hit_confirmation_04.wav</ShortName>
							<Path>SFX\Powers\PWR_20_Wales\sfx_power_k20_attack2_hit_confirmation_04_7FA8D501.wem</Path>
						</File>
						<File Id="490669572" Language="SFX">
							<ShortName>Powers\PWR_20_Wales\sfx_pwr_k20_hit_confirmation_stg_01.wav</ShortName>
							<Path>SFX\Powers\PWR_20_Wales\sfx_pwr_k20_hit_confirmation_stg_01_7FA8D501.wem</Path>
						</File>
						<File Id="609462577" Language="SFX">
							<ShortName>Powers\PWR_20_Wales\sfx_power_k20_attack2_hit_confirmation_07.wav</ShortName>
							<Path>SFX\Powers\PWR_20_Wales\sfx_power_k20_attack2_hit_confirmation_07_7FA8D501.wem</Path>
						</File>
						<File Id="690221786" Language="SFX">
							<ShortName>Powers\PWR_20_Wales\sfx_power_k20_attack2_hit_confirmation_06.wav</ShortName>
							<Path>SFX\Powers\PWR_20_Wales\sfx_power_k20_attack2_hit_confirmation_06_7FA8D501.wem</Path>
						</File>
						<File Id="774044017" Language="SFX">
							<ShortName>Powers\PWR_20_Wales\sfx_power_k20_attack2_hit_confirmation_02.wav</ShortName>
							<Path>SFX\Powers\PWR_20_Wales\sfx_power_k20_attack2_hit_confirmation_02_7FA8D501.wem</Path>
						</File>
						<File Id="858990869" Language="SFX">
							<ShortName>Powers\PWR_20_Wales\sfx_power_k20_attack2_hit_confirmation_03.wav</ShortName>
							<Path>SFX\Powers\PWR_20_Wales\sfx_power_k20_attack2_hit_confirmation_03_7FA8D501.wem</Path>
						</File>
						<File Id="950650672" Language="SFX">
							<ShortName>Powers\PWR_20_Wales\sfx_power_k20_attack2_hit_confirmation_01.wav</ShortName>
							<Path>SFX\Powers\PWR_20_Wales\sfx_power_k20_attack2_hit_confirmation_01_7FA8D501.wem</Path>
						</File>
					</IncludedMemoryFiles>
				</Event>
				<Event Id="3095165738" Name="AudioEvent_PWR_Wales_Attack2_Projectile_Start" ObjectPath="\Events\CHARACTER\KILLER\KLR_20_Wales\K20_POWER\AudioEvent_PWR_Wales_Attack2_Projectile_Start" GUID="{17E50258-3DD7-4F6E-AF7D-412D5EBA1DBB}" DurationType="OneShot" DurationMin="1.783314" DurationMax="2.207847">
					<IncludedMemoryFiles>
						<File Id="160007250" Language="SFX">
							<ShortName>Powers\PWR_20_Wales\sfx_power_k20_attack2_projectile_01.wav</ShortName>
							<Path>SFX\Powers\PWR_20_Wales\sfx_power_k20_attack2_projectile_01_7FA8D501.wem</Path>
						</File>
						<File Id="633357992" Language="SFX">
							<ShortName>Powers\PWR_20_Wales\sfx_power_k20_attack2_projectile_03_c.wav</ShortName>
							<Path>SFX\Powers\PWR_20_Wales\sfx_power_k20_attack2_projectile_03_c_7FA8D501.wem</Path>
						</File>
						<File Id="923835578" Language="SFX">
							<ShortName>Powers\PWR_20_Wales\sfx_power_k20_attack2_projectile_03_b.wav</ShortName>
							<Path>SFX\Powers\PWR_20_Wales\sfx_power_k20_attack2_projectile_03_b_7FA8D501.wem</Path>
						</File>
						<File Id="1010144891" Language="SFX">
							<ShortName>Powers\PWR_20_Wales\sfx_power_k20_attack2_projectile_03_a.wav</ShortName>
							<Path>SFX\Powers\PWR_20_Wales\sfx_power_k20_attack2_projectile_03_a_7FA8D501.wem</Path>
						</File>
					</IncludedMemoryFiles>
				</Event>
				<Event Id="1701553666" Name="AudioEvent_PWR_Wales_Attack2_Projectile_Stop" ObjectPath="\Events\CHARACTER\KILLER\KLR_20_Wales\K20_POWER\AudioEvent_PWR_Wales_Attack2_Projectile_Stop" GUID="{D49FE820-C77B-4CA1-B638-881FD3A65362}" MaxAttenuation="0.000000" DurationType="OneShot" DurationMin="0.000000" DurationMax="0.000000"/>
				<Event Id="3863173621" Name="AudioEvent_PWR_Wales_Attack2_Release" ObjectPath="\Events\CHARACTER\KILLER\KLR_20_Wales\K20_POWER\AudioEvent_PWR_Wales_Attack2_Release" GUID="{0B63F063-F056-4404-A9EA-0F630BF05689}" DurationType="OneShot" DurationMin="1.870887" DurationMax="2.357170">
					<IncludedMemoryFiles>
						<File Id="364594036" Language="SFX">
							<ShortName>Powers\PWR_20_Wales\sfx_power_k20_attack2_01.wav</ShortName>
							<Path>SFX\Powers\PWR_20_Wales\sfx_power_k20_attack2_01_7FA8D501.wem</Path>
						</File>
					</IncludedMemoryFiles>
				</Event>
				<Event Id="2972814440" Name="AudioEvent_PWR_Wales_DeathBed_Appear" ObjectPath="\Events\CHARACTER\KILLER\KLR_20_Wales\K20_POWER\AudioEvent_PWR_Wales_DeathBed_Appear" GUID="{A1917A99-2E24-4A8F-BE68-42DEDBA56E41}" DurationType="OneShot" DurationMin="4.696799" DurationMax="5.490864">
					<IncludedMemoryFiles>
						<File Id="929246737" Language="SFX">
							<ShortName>Powers\PWR_20_Wales\sfx_power_k20_deathbed_appear_stinger_01.wav</ShortName>
							<Path>SFX\Powers\PWR_20_Wales\sfx_power_k20_deathbed_appear_stinger_01_7FA8D501.wem</Path>
						</File>
						<File Id="936639975" Language="SFX">
							<ShortName>Powers\PWR_20_Wales\sfx_power_k20_deathbed_appear_stinger_02.wav</ShortName>
							<Path>SFX\Powers\PWR_20_Wales\sfx_power_k20_deathbed_appear_stinger_02_7FA8D501.wem</Path>
						</File>
					</IncludedMemoryFiles>
				</Event>
				<Event Id="3504270474" Name="AudioEvent_PWR_Wales_DeathBed_Crack_Start" ObjectPath="\Events\CHARACTER\KILLER\KLR_20_Wales\K20_POWER\AudioEvent_PWR_Wales_DeathBed_Crack_Start" GUID="{FB040437-4551-4A8E-8C80-EC762EB97A26}" MaxAttenuation="1700.000000" DurationType="OneShot" DurationMin="3.866667" DurationMax="3.866667">
					<IncludedMemoryFiles>
						<File Id="347317292" Language="SFX">
							<ShortName>Powers\PWR_20_Wales\sfx_pwr_k20_deathbed_crack_appear.wav</ShortName>
							<Path>SFX\Powers\PWR_20_Wales\sfx_pwr_k20_deathbed_crack_appear_7FA8D501.wem</Path>
						</File>
						<File Id="377810294" Language="SFX">
							<ShortName>Powers\PWR_20_Wales\sfx_pwr_k20_deathbed_crack_disappear.wav</ShortName>
							<Path>SFX\Powers\PWR_20_Wales\sfx_pwr_k20_deathbed_crack_disappear_7FA8D501.wem</Path>
						</File>
					</IncludedMemoryFiles>
				</Event>
				<Event Id="2897539810" Name="AudioEvent_PWR_Wales_DeathBed_Crack_Stop" ObjectPath="\Events\CHARACTER\KILLER\KLR_20_Wales\K20_POWER\AudioEvent_PWR_Wales_DeathBed_Crack_Stop" GUID="{BE5C9602-A68E-4195-968A-99D4ACC74C12}" MaxAttenuation="1700.000000" DurationType="OneShot" DurationMin="1.533333" DurationMax="1.533333">
					<IncludedMemoryFiles>
						<File Id="377810294" Language="SFX">
							<ShortName>Powers\PWR_20_Wales\sfx_pwr_k20_deathbed_crack_disappear.wav</ShortName>
							<Path>SFX\Powers\PWR_20_Wales\sfx_pwr_k20_deathbed_crack_disappear_7FA8D501.wem</Path>
						</File>
					</IncludedMemoryFiles>
				</Event>
				<Event Id="3559750152" Name="AudioEvent_PWR_Wales_DeathBed_Hit_Bend" ObjectPath="\Events\CHARACTER\KILLER\KLR_20_Wales\K20_POWER\AudioEvent_PWR_Wales_DeathBed_Hit_Bend" GUID="{F5C7CF3F-8433-432D-B4CB-A4CDA29A4271}" MaxAttenuation="1700.000000" DurationType="OneShot" DurationMin="0.800000" DurationMax="1.633333">
					<IncludedMemoryFiles>
						<File Id="179617816" Language="SFX">
							<ShortName>Powers\PWR_20_Wales\sfx_pwr_k20_deathbed_hit_bend_02.wav</ShortName>
							<Path>SFX\Powers\PWR_20_Wales\sfx_pwr_k20_deathbed_hit_bend_02_7FA8D501.wem</Path>
						</File>
						<File Id="294783567" Language="SFX">
							<ShortName>Powers\PWR_20_Wales\sfx_pwr_k20_deathbed_hit_bend_01.wav</ShortName>
							<Path>SFX\Powers\PWR_20_Wales\sfx_pwr_k20_deathbed_hit_bend_01_7FA8D501.wem</Path>
						</File>
						<File Id="666224782" Language="SFX">
							<ShortName>Powers\PWR_20_Wales\sfx_pwr_k20_deathbed_hit_bend_03.wav</ShortName>
							<Path>SFX\Powers\PWR_20_Wales\sfx_pwr_k20_deathbed_hit_bend_03_7FA8D501.wem</Path>
						</File>
					</IncludedMemoryFiles>
				</Event>
				<Event Id="2699858118" Name="AudioEvent_PWR_Wales_DeathBed_Rescue_Bend" ObjectPath="\Events\CHARACTER\KILLER\KLR_20_Wales\K20_POWER\AudioEvent_PWR_Wales_DeathBed_Rescue_Bend" GUID="{DB7DAA33-4EA2-4821-884F-0CFFCA8B08E4}" MaxAttenuation="1700.000000" DurationType="OneShot" DurationMin="0.565583" DurationMax="1.154854">
					<IncludedMemoryFiles>
						<File Id="230206482" Language="SFX">
							<ShortName>Powers\PWR_20_Wales\sfx_pwr_k20_deathbed_open_bend_01.wav</ShortName>
							<Path>SFX\Powers\PWR_20_Wales\sfx_pwr_k20_deathbed_open_bend_01_7FA8D501.wem</Path>
						</File>
						<File Id="406578864" Language="SFX">
							<ShortName>Powers\PWR_20_Wales\sfx_pwr_k20_deathbed_open_bend_02.wav</ShortName>
							<Path>SFX\Powers\PWR_20_Wales\sfx_pwr_k20_deathbed_open_bend_02_7FA8D501.wem</Path>
						</File>
						<File Id="473191302" Language="SFX">
							<ShortName>Powers\PWR_20_Wales\sfx_pwr_k20_deathbed_open_bend_03.wav</ShortName>
							<Path>SFX\Powers\PWR_20_Wales\sfx_pwr_k20_deathbed_open_bend_03_7FA8D501.wem</Path>
						</File>
					</IncludedMemoryFiles>
				</Event>
				<Event Id="2230668134" Name="AudioEvent_PWR_Wales_DeathBed_Rescue_Dissolve" ObjectPath="\Events\CHARACTER\KILLER\KLR_20_Wales\K20_POWER\AudioEvent_PWR_Wales_DeathBed_Rescue_Dissolve" GUID="{C7171E9A-83EA-4D18-B595-20C844584188}" MaxAttenuation="1700.000000" DurationType="OneShot" DurationMin="2.400000" DurationMax="3.093333">
					<IncludedMemoryFiles>
						<File Id="131625501" Language="SFX">
							<ShortName>Powers\PWR_20_Wales\sfx_pwr_k20_deathbed_rescue_dissolve_03.wav</ShortName>
							<Path>SFX\Powers\PWR_20_Wales\sfx_pwr_k20_deathbed_rescue_dissolve_03_7FA8D501.wem</Path>
						</File>
						<File Id="594037135" Language="SFX">
							<ShortName>Powers\PWR_20_Wales\sfx_pwr_k20_deathbed_rescue_dissolve_02.wav</ShortName>
							<Path>SFX\Powers\PWR_20_Wales\sfx_pwr_k20_deathbed_rescue_dissolve_02_7FA8D501.wem</Path>
						</File>
						<File Id="953162948" Language="SFX">
							<ShortName>Powers\PWR_20_Wales\sfx_pwr_k20_deathbed_rescue_dissolve_01.wav</ShortName>
							<Path>SFX\Powers\PWR_20_Wales\sfx_pwr_k20_deathbed_rescue_dissolve_01_7FA8D501.wem</Path>
						</File>
					</IncludedMemoryFiles>
				</Event>
				<Event Id="4166279100" Name="AudioEvent_PWR_Wales_Trail_Blocked" ObjectPath="\Events\CHARACTER\KILLER\KLR_20_Wales\K20_POWER\AudioEvent_PWR_Wales_Trail_Blocked" GUID="{29032F16-9806-4557-8A7E-038C471EAF5F}" MaxAttenuation="850.000000" DurationType="OneShot" DurationMin="0.291512" DurationMax="0.494139">
					<IncludedMemoryFiles>
						<File Id="94576943" Language="SFX">
							<ShortName>Powers\PWR_20_Wales\sfx_power_k20_trail_draw_rock_single_disto_14.wav</ShortName>
							<Path>SFX\Powers\PWR_20_Wales\sfx_power_k20_trail_draw_rock_single_disto_14_2F6EB96E.wem</Path>
						</File>
						<File Id="108376972" Language="SFX">
							<ShortName>Powers\PWR_20_Wales\sfx_power_k20_trail_draw_rock_single_disto_05.wav</ShortName>
							<Path>SFX\Powers\PWR_20_Wales\sfx_power_k20_trail_draw_rock_single_disto_05_AEC52475.wem</Path>
						</File>
						<File Id="534351328" Language="SFX">
							<ShortName>Powers\PWR_20_Wales\sfx_power_k20_trail_draw_rock_single_disto_08.wav</ShortName>
							<Path>SFX\Powers\PWR_20_Wales\sfx_power_k20_trail_draw_rock_single_disto_08_7AC0F2BF.wem</Path>
						</File>
						<File Id="662604331" Language="SFX">
							<ShortName>Powers\PWR_20_Wales\sfx_power_k20_trail_draw_rock_single_disto_16.wav</ShortName>
							<Path>SFX\Powers\PWR_20_Wales\sfx_power_k20_trail_draw_rock_single_disto_16_77D7A2FF.wem</Path>
						</File>
						<File Id="674647700" Language="SFX">
							<ShortName>Powers\PWR_20_Wales\sfx_power_k20_trail_draw_rock_single_disto_09.wav</ShortName>
							<Path>SFX\Powers\PWR_20_Wales\sfx_power_k20_trail_draw_rock_single_disto_09_0866D899.wem</Path>
						</File>
						<File Id="763913854" Language="SFX">
							<ShortName>Powers\PWR_20_Wales\sfx_power_k20_trail_draw_rock_single_disto_11.wav</ShortName>
							<Path>SFX\Powers\PWR_20_Wales\sfx_power_k20_trail_draw_rock_single_disto_11_3A9C91AC.wem</Path>
						</File>
						<File Id="778804294" Language="SFX">
							<ShortName>Powers\PWR_20_Wales\sfx_power_k20_trail_draw_rock_single_disto_12.wav</ShortName>
							<Path>SFX\Powers\PWR_20_Wales\sfx_power_k20_trail_draw_rock_single_disto_12_5E579854.wem</Path>
						</File>
						<File Id="808920599" Language="SFX">
							<ShortName>Powers\PWR_20_Wales\sfx_power_k20_trail_draw_rock_single_disto_10.wav</ShortName>
							<Path>SFX\Powers\PWR_20_Wales\sfx_power_k20_trail_draw_rock_single_disto_10_8B6A93B5.wem</Path>
						</File>
						<File Id="884189139" Language="SFX">
							<ShortName>Powers\PWR_20_Wales\sfx_power_k20_trail_draw_rock_single_disto_15.wav</ShortName>
							<Path>SFX\Powers\PWR_20_Wales\sfx_power_k20_trail_draw_rock_single_disto_15_445EC802.wem</Path>
						</File>
						<File Id="1022612075" Language="SFX">
							<ShortName>Powers\PWR_20_Wales\sfx_power_k20_trail_draw_rock_single_disto_06.wav</ShortName>
							<Path>SFX\Powers\PWR_20_Wales\sfx_power_k20_trail_draw_rock_single_disto_06_C6B6B4D0.wem</Path>
						</File>
						<File Id="1045332348" Language="SFX">
							<ShortName>Powers\PWR_20_Wales\sfx_power_k20_trail_draw_rock_single_disto_07.wav</ShortName>
							<Path>SFX\Powers\PWR_20_Wales\sfx_power_k20_trail_draw_rock_single_disto_07_5E9C3608.wem</Path>
						</File>
					</IncludedMemoryFiles>
				</Event>
				<Event Id="163728019" Name="AudioEvent_PWR_Wales_Trail_Draw_Start" ObjectPath="\Events\CHARACTER\KILLER\KLR_20_Wales\K20_POWER\AudioEvent_PWR_Wales_Trail_Draw_Start" GUID="{FE365CD7-C461-4F46-B8FB-07C29840CB20}" MaxAttenuation="1700.000000" DurationType="Infinite">
					<IncludedMemoryFiles>
						<File Id="63521640" Language="SFX">
							<ShortName>Powers\PWR_20_Wales\sfx_power_k20_trail_draw_rock_single_disto_02.wav</ShortName>
							<Path>SFX\Powers\PWR_20_Wales\sfx_power_k20_trail_draw_rock_single_disto_02_7FA8D501.wem</Path>
						</File>
						<File Id="171510677" Language="SFX">
							<ShortName>Powers\PWR_20_Wales\sfx_power_k20_trail_draw_rock_single_disto_14.wav</ShortName>
							<Path>SFX\Powers\PWR_20_Wales\sfx_power_k20_trail_draw_rock_single_disto_14_7FA8D501.wem</Path>
						</File>
						<File Id="206470488" Language="SFX">
							<ShortName>Powers\PWR_20_Wales\sfx_power_k20_trail_draw_rock_single_disto_12.wav</ShortName>
							<Path>SFX\Powers\PWR_20_Wales\sfx_power_k20_trail_draw_rock_single_disto_12_7FA8D501.wem</Path>
						</File>
						<File Id="246759785" Language="SFX">
							<ShortName>Powers\PWR_20_Wales\sfx_power_k20_trail_draw_rock_single_disto_09.wav</ShortName>
							<Path>SFX\Powers\PWR_20_Wales\sfx_power_k20_trail_draw_rock_single_disto_09_7FA8D501.wem</Path>
						</File>
						<File Id="284228830" Language="SFX">
							<ShortName>Powers\PWR_20_Wales\sfx_power_k20_trail_draw_rock_single_disto_10.wav</ShortName>
							<Path>SFX\Powers\PWR_20_Wales\sfx_power_k20_trail_draw_rock_single_disto_10_7FA8D501.wem</Path>
						</File>
						<File Id="302346277" Language="SFX">
							<ShortName>Powers\PWR_20_Wales\sfx_power_k20_trail_draw_rock_single_disto_04.wav</ShortName>
							<Path>SFX\Powers\PWR_20_Wales\sfx_power_k20_trail_draw_rock_single_disto_04_7FA8D501.wem</Path>
						</File>
						<File Id="417638837" Language="SFX">
							<ShortName>Powers\PWR_20_Wales\sfx_power_k20_trail_draw_rock_single_disto_08.wav</ShortName>
							<Path>SFX\Powers\PWR_20_Wales\sfx_power_k20_trail_draw_rock_single_disto_08_7FA8D501.wem</Path>
						</File>
						<File Id="432448676" Language="SFX">
							<ShortName>Powers\PWR_20_Wales\sfx_power_k20_trail_draw_rock_single_disto_01.wav</ShortName>
							<Path>SFX\Powers\PWR_20_Wales\sfx_power_k20_trail_draw_rock_single_disto_01_7FA8D501.wem</Path>
						</File>
						<File Id="620035400" Language="SFX">
							<ShortName>Powers\PWR_20_Wales\sfx_power_k20_trail_draw_rock_single_disto_16.wav</ShortName>
							<Path>SFX\Powers\PWR_20_Wales\sfx_power_k20_trail_draw_rock_single_disto_16_7FA8D501.wem</Path>
						</File>
						<File Id="653568569" Language="SFX">
							<ShortName>Powers\PWR_20_Wales\sfx_power_k20_trail_draw_loop_01.wav</ShortName>
							<Path>SFX\Powers\PWR_20_Wales\sfx_power_k20_trail_draw_loop_01_256CDB0F.wem</Path>
						</File>
						<File Id="696863187" Language="SFX">
							<ShortName>Powers\PWR_20_Wales\sfx_power_k20_trail_draw_rock_single_disto_15.wav</ShortName>
							<Path>SFX\Powers\PWR_20_Wales\sfx_power_k20_trail_draw_rock_single_disto_15_7FA8D501.wem</Path>
						</File>
						<File Id="726783964" Language="SFX">
							<ShortName>Powers\PWR_20_Wales\sfx_power_k20_trail_draw_rock_single_disto_05.wav</ShortName>
							<Path>SFX\Powers\PWR_20_Wales\sfx_power_k20_trail_draw_rock_single_disto_05_7FA8D501.wem</Path>
						</File>
						<File Id="820756736" Language="SFX">
							<ShortName>Powers\PWR_20_Wales\sfx_power_k20_trail_draw_rock_single_disto_06.wav</ShortName>
							<Path>SFX\Powers\PWR_20_Wales\sfx_power_k20_trail_draw_rock_single_disto_06_7FA8D501.wem</Path>
						</File>
						<File Id="857111754" Language="SFX">
							<ShortName>Powers\PWR_20_Wales\sfx_power_k20_trail_draw_rock_single_disto_03.wav</ShortName>
							<Path>SFX\Powers\PWR_20_Wales\sfx_power_k20_trail_draw_rock_single_disto_03_7FA8D501.wem</Path>
						</File>
						<File Id="984057903" Language="SFX">
							<ShortName>Powers\PWR_20_Wales\sfx_power_k20_trail_draw_rock_single_disto_11.wav</ShortName>
							<Path>SFX\Powers\PWR_20_Wales\sfx_power_k20_trail_draw_rock_single_disto_11_7FA8D501.wem</Path>
						</File>
						<File Id="994093661" Language="SFX">
							<ShortName>Powers\PWR_20_Wales\sfx_power_k20_trail_draw_rock_single_disto_13.wav</ShortName>
							<Path>SFX\Powers\PWR_20_Wales\sfx_power_k20_trail_draw_rock_single_disto_13_7FA8D501.wem</Path>
						</File>
						<File Id="997971836" Language="SFX">
							<ShortName>Powers\PWR_20_Wales\sfx_power_k20_trail_draw_rock_single_disto_07.wav</ShortName>
							<Path>SFX\Powers\PWR_20_Wales\sfx_power_k20_trail_draw_rock_single_disto_07_7FA8D501.wem</Path>
						</File>
					</IncludedMemoryFiles>
				</Event>
				<Event Id="38584145" Name="AudioEvent_PWR_Wales_Trail_Draw_Stop" ObjectPath="\Events\CHARACTER\KILLER\KLR_20_Wales\K20_POWER\AudioEvent_PWR_Wales_Trail_Draw_Stop" GUID="{B85A9EB9-36C7-47EA-A279-2BB7A4AD6DB6}" MaxAttenuation="0.000000" DurationType="OneShot" DurationMin="0.000000" DurationMax="0.000000"/>
				<Event Id="4266755183" Name="AudioEvent_PWR_Wales_Trail_Emitter_Start" ObjectPath="\Events\CHARACTER\KILLER\KLR_20_Wales\K20_POWER\AudioEvent_PWR_Wales_Trail_Emitter_Start" GUID="{53D3CF19-57B8-435D-ACB5-CF24E57B9437}" MaxAttenuation="800.000000" DurationType="Infinite">
					<IncludedMemoryFiles>
						<File Id="246342557" Language="SFX">
							<ShortName>Powers\PWR_20_Wales\sfx_power_k20_trail_emitter_loop_01.wav</ShortName>
							<Path>SFX\Powers\PWR_20_Wales\sfx_power_k20_trail_emitter_loop_01_256CDB0F.wem</Path>
						</File>
					</IncludedMemoryFiles>
				</Event>
				<Event Id="3085313397" Name="AudioEvent_PWR_Wales_Trail_Emitter_Stop" ObjectPath="\Events\CHARACTER\KILLER\KLR_20_Wales\K20_POWER\AudioEvent_PWR_Wales_Trail_Emitter_Stop" GUID="{BC653C0C-31BF-44ED-8B29-D25E00819FF4}" MaxAttenuation="0.000000" DurationType="OneShot" DurationMin="0.000000" DurationMax="0.000000"/>
			</IncludedEvents>
			<IncludedMemoryFiles>
				<File Id="132797613" Language="SFX">
					<ShortName>Music\mu_terrorradius_k20_layer_04.wav</ShortName>
					<Path>SFX\Music\mu_terrorradius_k20_layer_04_256CDB0F.wem</Path>
				</File>
				<File Id="231365864" Language="SFX">
					<ShortName>Music\mu_terrorradius_k20_layer_03.wav</ShortName>
					<Path>SFX\Music\mu_terrorradius_k20_layer_03_256CDB0F.wem</Path>
				</File>
				<File Id="632037820" Language="SFX">
					<ShortName>Music\mu_terrorradius_k20_layer_01.wav</ShortName>
					<Path>SFX\Music\mu_terrorradius_k20_layer_01_256CDB0F.wem</Path>
				</File>
				<File Id="653031648" Language="SFX">
					<ShortName>Music\mu_terrorradius_k20_layer_02.wav</ShortName>
					<Path>SFX\Music\mu_terrorradius_k20_layer_02_256CDB0F.wem</Path>
				</File>
			</IncludedMemoryFiles>
			<GameParameters>
				<GameParameter Id="1343933513" Name="AudioRTPC_VOL_KLR_GRUNT" ObjectPath="\Game Parameters\RTPC_VOLUME\AudioRTPC_VOL_KLR_GRUNT" GUID="{BAAB17DD-4958-4CD7-AEA6-A2737955A39A}"/>
				<GameParameter Id="1976939065" Name="AudioRTPC_KLR_20_Wales_Moving_Speed" ObjectPath="\Game Parameters\RTPC_CHARACTER\RTPC_K20_Wales\AudioRTPC_KLR_20_Wales_Moving_Speed" GUID="{B351C602-048E-4240-B561-C778B5D85A92}"/>
				<GameParameter Id="2444086592" Name="AudioRTPC_Proximity_Terror_Radius" ObjectPath="\Game Parameters\RTPC_CHARACTER\RTPC_00_COMMON\AudioRTPC_Proximity_Terror_Radius" GUID="{B90C8BF7-27D1-46A0-8417-5EA7C60184A3}"/>
				<GameParameter Id="2935614212" Name="AudioRTPC_Chase_Survivor" ObjectPath="\Game Parameters\RTPC_CHARACTER\RTPC_00_COMMON\AudioRTPC_Chase_Survivor" GUID="{173C4D0D-11E9-4F47-871B-1284E8907774}"/>
				<GameParameter Id="4096507154" Name="AudioRTPC_Listener_Angle_Object_Relative" ObjectPath="\Game Parameters\RTPC_WORLD\AudioRTPC_Listener_Angle_Object_Relative" GUID="{4A4DA43C-9F93-4C5C-A3EF-C2E12ACD41D3}"/>
			</GameParameters>
			<SwitchGroups>
				<SwitchGroup Id="1168819874" Name="AudioSwitchSurface" ObjectPath="\Switches\SWITCH_COMMON\AudioSwitchSurface" GUID="{371C038E-C81E-4B1E-BEF0-AC9809AE0B13}">
					<Switches>
						<Switch Id="2058049674" Name="Wood" ObjectPath="\Switches\SWITCH_COMMON\AudioSwitchSurface\Wood" GUID="{220AA47D-7E65-4864-A865-719DAC7D0078}"/>
						<Switch Id="2315975534" Name="Metal_Hard" ObjectPath="\Switches\SWITCH_COMMON\AudioSwitchSurface\Metal_Hard" GUID="{927B6344-7A96-4DF4-AFE4-4E141E97A81F}"/>
						<Switch Id="712897245" Name="Mud" ObjectPath="\Switches\SWITCH_COMMON\AudioSwitchSurface\Mud" GUID="{1974DF19-3EAC-4718-94A9-7C7895513BA6}"/>
						<Switch Id="841620460" Name="Concrete" ObjectPath="\Switches\SWITCH_COMMON\AudioSwitchSurface\Concrete" GUID="{9947A5B8-0A0B-4897-BF44-2905F208E8DD}"/>
						<Switch Id="2195636714" Name="Dirt" ObjectPath="\Switches\SWITCH_COMMON\AudioSwitchSurface\Dirt" GUID="{F8694AFD-F385-4983-A2F5-5B159E8ED9D2}"/>
						<Switch Id="2185786256" Name="Gravel" ObjectPath="\Switches\SWITCH_COMMON\AudioSwitchSurface\Gravel" GUID="{175357DC-ECFA-4355-93E2-1A75AFA11C43}"/>
						<Switch Id="504532776" Name="Brick" ObjectPath="\Switches\SWITCH_COMMON\AudioSwitchSurface\Brick" GUID="{7CFDEF5B-7E20-4AA0-95F3-2DEDB396AF1F}"/>
						<Switch Id="2932679629" Name="Vegetation" ObjectPath="\Switches\SWITCH_COMMON\AudioSwitchSurface\Vegetation" GUID="{A941FD53-8C7E-4702-8A7E-95B4CFB4DE52}"/>
						<Switch Id="3787826983" Name="Corn" ObjectPath="\Switches\SWITCH_COMMON\AudioSwitchSurface\Corn" GUID="{41A7F3B6-4B78-421A-BAD3-16E485BDB8D0}"/>
						<Switch Id="3681786913" Name="Metal_Soft" ObjectPath="\Switches\SWITCH_COMMON\AudioSwitchSurface\Metal_Soft" GUID="{5E16CA95-78BB-463D-B626-96B1DCBF0FDD}"/>
						<Switch Id="2981489164" Name="FleshDry" ObjectPath="\Switches\SWITCH_COMMON\AudioSwitchSurface\FleshDry" GUID="{A602BDEB-16F8-46CD-BB54-CFE585D15F02}"/>
						<Switch Id="3322072369" Name="Tree" ObjectPath="\Switches\SWITCH_COMMON\AudioSwitchSurface\Tree" GUID="{646F7389-CAE6-4F36-AEB3-BA5883FFBC7A}"/>
						<Switch Id="2144363834" Name="Rock" ObjectPath="\Switches\SWITCH_COMMON\AudioSwitchSurface\Rock" GUID="{A970F4EA-165B-4AC1-A78C-73F51FC9EA9D}"/>
						<Switch Id="3934470635" Name="Blood" ObjectPath="\Switches\SWITCH_COMMON\AudioSwitchSurface\Blood" GUID="{46A7CC2C-1CCD-4037-9FB7-52AD43498872}"/>
						<Switch Id="2654748154" Name="Water" ObjectPath="\Switches\SWITCH_COMMON\AudioSwitchSurface\Water" GUID="{01B02E8C-F215-4C55-A4A7-703EC37B779F}"/>
						<Switch Id="2449969375" Name="Glass" ObjectPath="\Switches\SWITCH_COMMON\AudioSwitchSurface\Glass" GUID="{D024D7D1-8B15-432A-933B-97316C21555A}"/>
						<Switch Id="3562804263" Name="ChainLinkFence" ObjectPath="\Switches\SWITCH_COMMON\AudioSwitchSurface\ChainLinkFence" GUID="{300CE055-A091-4BE3-A8A0-DE735DDACBE8}"/>
						<Switch Id="660835419" Name="Plastic" ObjectPath="\Switches\SWITCH_COMMON\AudioSwitchSurface\Plastic" GUID="{E10DE96C-22AC-408E-9FC6-443E95F6B542}"/>
						<Switch Id="2412606308" Name="Carpet" ObjectPath="\Switches\SWITCH_COMMON\AudioSwitchSurface\Carpet" GUID="{F167B121-F497-496D-A248-9FF4BF749539}"/>
						<Switch Id="803837735" Name="Sand" ObjectPath="\Switches\SWITCH_COMMON\AudioSwitchSurface\Sand" GUID="{33C94342-DC4C-4551-AE18-3B244ECA0689}"/>
						<Switch Id="2108779961" Name="Wall" ObjectPath="\Switches\SWITCH_COMMON\AudioSwitchSurface\Wall" GUID="{131534FE-9431-446B-854D-1E81BA3C77E7}"/>
						<Switch Id="787898836" Name="Snow" ObjectPath="\Switches\SWITCH_COMMON\AudioSwitchSurface\Snow" GUID="{61C0A8D2-F421-465E-A55C-823BB4931283}"/>
						<Switch Id="3825060929" Name="Metal_Grid" ObjectPath="\Switches\SWITCH_COMMON\AudioSwitchSurface\Metal_Grid" GUID="{2792490C-9C7E-402A-B630-E1AEE10B67B0}"/>
						<Switch Id="2736974230" Name="Tarp" ObjectPath="\Switches\SWITCH_COMMON\AudioSwitchSurface\Tarp" GUID="{834AF73E-2FDA-4B1F-ABF8-7E926EA04F5E}"/>
						<Switch Id="3841404889" Name="Plexiglass" ObjectPath="\Switches\SWITCH_COMMON\AudioSwitchSurface\Plexiglass" GUID="{816BCA21-2268-4487-BF96-A5B26BCB03FC}"/>
						<Switch Id="3006065224" Name="Barrel_Plastic" ObjectPath="\Switches\SWITCH_COMMON\AudioSwitchSurface\Barrel_Plastic" GUID="{C1C58031-724C-47CC-9412-B4B8142690DD}"/>
						<Switch Id="2507846665" Name="Barrel_Metal" ObjectPath="\Switches\SWITCH_COMMON\AudioSwitchSurface\Barrel_Metal" GUID="{2E7DBB43-636B-4B2D-8A1E-F99FB66D3ACB}"/>
						<Switch Id="3670307564" Name="Drywall" ObjectPath="\Switches\SWITCH_COMMON\AudioSwitchSurface\Drywall" GUID="{D1454CB1-47C3-40C2-A2DE-B7D285618338}"/>
						<Switch Id="3023765155" Name="TECH_Debris_Rock" ObjectPath="\Switches\SWITCH_COMMON\AudioSwitchSurface\TECH_Debris_Rock" GUID="{32437BA7-BDFA-4FD5-9B9B-D294FFFD6D55}"/>
						<Switch Id="2003165988" Name="TECH_Debris_Glass" ObjectPath="\Switches\SWITCH_COMMON\AudioSwitchSurface\TECH_Debris_Glass" GUID="{38536567-1A12-4FD1-8DCF-06603790A598}"/>
						<Switch Id="1675720334" Name="TECH_Debris_Trash" ObjectPath="\Switches\SWITCH_COMMON\AudioSwitchSurface\TECH_Debris_Trash" GUID="{48A06FE5-D77E-440C-BC12-44D3DFE248E2}"/>
						<Switch Id="3006696107" Name="Tire" ObjectPath="\Switches\SWITCH_COMMON\AudioSwitchSurface\Tire" GUID="{978DAF7D-37D9-4EB1-BF47-9FAE7D88E73D}"/>
						<Switch Id="2243064231" Name="FleshJuicy" ObjectPath="\Switches\SWITCH_COMMON\AudioSwitchSurface\FleshJuicy" GUID="{83EDD421-A376-401D-9D56-3CC8596D4C20}"/>
						<Switch Id="782826392" Name="Default" ObjectPath="\Switches\SWITCH_COMMON\AudioSwitchSurface\Default" GUID="{82BAB65C-92F7-4F63-990C-4F5495B4979B}"/>
						<Switch Id="1229756253" Name="Cardboard" ObjectPath="\Switches\SWITCH_COMMON\AudioSwitchSurface\Cardboard" GUID="{15062674-8B2F-4664-AEB6-B4178F782C33}"/>
						<Switch Id="329716760" Name="Typewriter" ObjectPath="\Switches\SWITCH_COMMON\AudioSwitchSurface\Typewriter" GUID="{0A3F18F3-23BA-4260-80B0-6B8B2BE7F164}"/>
					</Switches>
				</SwitchGroup>
				<SwitchGroup Id="2003718045" Name="AudioSwitchStatesSurvivor" ObjectPath="\Switches\SWITCH_SURVIVOR\AudioSwitchStatesSurvivor" GUID="{A172B188-385A-4B2F-9B5B-01C1D0763E22}">
					<Switches>
						<Switch Id="1160234136" Name="Normal" ObjectPath="\Switches\SWITCH_SURVIVOR\AudioSwitchStatesSurvivor\Normal" GUID="{4634728D-A6EC-463F-98B7-88625AA203FB}"/>
						<Switch Id="3863236874" Name="Running" ObjectPath="\Switches\SWITCH_SURVIVOR\AudioSwitchStatesSurvivor\Running" GUID="{C122D54D-7534-40F3-9278-C4B3885FC8A1}"/>
						<Switch Id="2044049779" Name="Dead" ObjectPath="\Switches\SWITCH_SURVIVOR\AudioSwitchStatesSurvivor\Dead" GUID="{3AAC6EB5-396F-445C-9C9B-7F35A2688A75}"/>
						<Switch Id="3413347345" Name="Healing" ObjectPath="\Switches\SWITCH_SURVIVOR\AudioSwitchStatesSurvivor\Healing" GUID="{23B62077-3C78-4A2C-9ED3-6207E562EFB0}"/>
						<Switch Id="1848633330" Name="Hooked_Part1" ObjectPath="\Switches\SWITCH_SURVIVOR\AudioSwitchStatesSurvivor\Hooked_Part1" GUID="{05374D88-4159-48FB-9221-5804D3776A9D}"/>
						<Switch Id="559827443" Name="Captured" ObjectPath="\Switches\SWITCH_SURVIVOR\AudioSwitchStatesSurvivor\Captured" GUID="{4B05EE76-2F40-47BF-B51C-3D49C36C540B}"/>
						<Switch Id="2860195132" Name="Injured" ObjectPath="\Switches\SWITCH_SURVIVOR\AudioSwitchStatesSurvivor\Injured" GUID="{C6A55A58-493C-4921-A35A-7A4B7296A933}"/>
						<Switch Id="3328495488" Name="Dying" ObjectPath="\Switches\SWITCH_SURVIVOR\AudioSwitchStatesSurvivor\Dying" GUID="{87ED9576-D64C-486B-80A5-29160DA2BBC0}"/>
						<Switch Id="1848633329" Name="Hooked_Part2" ObjectPath="\Switches\SWITCH_SURVIVOR\AudioSwitchStatesSurvivor\Hooked_Part2" GUID="{474E2D86-48C4-4A2B-B5ED-A2D234E85A86}"/>
						<Switch Id="1919908153" Name="Normal_Crouch" ObjectPath="\Switches\SWITCH_SURVIVOR\AudioSwitchStatesSurvivor\Normal_Crouch" GUID="{E376616F-981E-41F4-9032-AB5D789371F0}"/>
						<Switch Id="121290285" Name="Injured_Crouch" ObjectPath="\Switches\SWITCH_SURVIVOR\AudioSwitchStatesSurvivor\Injured_Crouch" GUID="{B5F3498F-7451-47C5-B4EF-A1D4520FB19C}"/>
						<Switch Id="3200746917" Name="Choked" ObjectPath="\Switches\SWITCH_SURVIVOR\AudioSwitchStatesSurvivor\Choked" GUID="{1C4E6EB1-25A8-4755-BDBA-D8E79CCFD3CE}"/>
						<Switch Id="3094692510" Name="Injured_Hiding" ObjectPath="\Switches\SWITCH_SURVIVOR\AudioSwitchStatesSurvivor\Injured_Hiding" GUID="{54A0B897-2A42-4AE1-B0D5-CA909A8C5F16}"/>
						<Switch Id="63215442" Name="Normal_Hiding" ObjectPath="\Switches\SWITCH_SURVIVOR\AudioSwitchStatesSurvivor\Normal_Hiding" GUID="{21B70A73-E2F6-4A2B-B152-265C2483D367}"/>
					</Switches>
				</SwitchGroup>
				<SwitchGroup Id="3548994684" Name="AudioSwitchProximity" ObjectPath="\Switches\SWITCH_SURVIVOR\AudioSwitchProximity" GUID="{A238147F-8756-470E-AC66-0AFAF133FD8A}">
					<Switches>
						<Switch Id="4248742144" Name="Nothing" ObjectPath="\Switches\SWITCH_SURVIVOR\AudioSwitchProximity\Nothing" GUID="{5B89779D-7E3C-4C6A-ACE5-5EDAC3AF6402}"/>
						<Switch Id="1256202815" Name="Play" ObjectPath="\Switches\SWITCH_SURVIVOR\AudioSwitchProximity\Play" GUID="{40D8D63D-A241-4B30-8DD9-892C554BEA5C}"/>
					</Switches>
				</SwitchGroup>
			</SwitchGroups>
		</SoundBank>
	</SoundBanks>
</SoundBanksInfo>
